{"data":[ { "_id" : { "$oid" : "60d1cff136f48c39416c85d3"} , "執照類別" : "建造執照" , "核發執照字號" : "82府都建建字第06602號" , "原領執照字號" : "" , "變更設計次數" : "00" , "基地面積" : "0㎡" , "建築面積" : "0㎡" , "總樓地板面積" : "0㎡" , "建築物高度" : "0ｍ" , "地下避難面積" : "0㎡" , "法定空地面積" : "0㎡" , "建造類別" : "" , "構造別" : "" , "地上層數" : "0層" , "地下層數" : "0層" , "棟數" : "0棟" , "戶數" : "0戶" , "起造人代表人" : "" , "起造人地址" : "" , "設計人" : "" , "監造人" : "" , "承造人" : "" , "雜項工作物" : "" , "停車空間" : "法定0輛，獎勵0輛，自設0輛" , "發照日期" : "年月日" , "實際開工日期" : "年月日" , "竣工日期" : "年月日" , "土地使用分區" : "" , "建築物用途" : "" , "工程造價" : "" , "qtime" : "" , "樓層概要" : [ ] , "地號" : [ ] , "門牌" : [ ] , "縣市別" : "台中市"} , { "_id" : { "$oid" : "60d1cff136f48c39416c85d4"} , "執照類別" : "建造執照" , "核發執照字號" : "82府都建建字第06603號" , "原領執照字號" : "" , "變更設計次數" : "00" , "基地面積" : "0㎡" , "建築面積" : "0㎡" , "總樓地板面積" : "0㎡" , "建築物高度" : "0ｍ" , "地下避難面積" : "0㎡" , "法定空地面積" : "0㎡" , "建造類別" : "" , "構造別" : "" , "地上層數" : "0層" , "地下層數" : "0層" , "棟數" : "0棟" , "戶數" : "0戶" , "起造人代表人" : "" , "起造人地址" : "" , "設計人" : "" , "監造人" : "" , "承造人" : "" , "雜項工作物" : "" , "停車空間" : "法定0輛，獎勵0輛，自設0輛" , "發照日期" : "年月日" , "實際開工日期" : "年月日" , "竣工日期" : "年月日" , "土地使用分區" : "" , "建築物用途" : "" , "工程造價" : "" , "qtime" : "" , "樓層概要" : [ ] , "地號" : [ ] , "門牌" : [ ] , "縣市別" : "台中市"} , { "_id" : { "$oid" : "60d1cff136f48c39416c85d5"} , "執照類別" : "建造執照" , "核發執照字號" : "82府都建建字第06604號" , "原領執照字號" : "" , "變更設計次數" : "00" , "基地面積" : "0㎡" , "建築面積" : "0㎡" , "總樓地板面積" : "0㎡" , "建築物高度" : "0ｍ" , "地下避難面積" : "0㎡" , "法定空地面積" : "0㎡" , "建造類別" : "" , "構造別" : "" , "地上層數" : "0層" , "地下層數" : "0層" , "棟數" : "0棟" , "戶數" : "0戶" , "起造人代表人" : "" , "起造人地址" : "" , "設計人" : "" , "監造人" : "" , "承造人" : "" , "雜項工作物" : "" , "停車空間" : "法定0輛，獎勵0輛，自設0輛" , "發照日期" : "年月日" , "實際開工日期" : "年月日" , "竣工日期" : "年月日" , "土地使用分區" : "" , "建築物用途" : "" , "工程造價" : "" , "qtime" : "" , "樓層概要" : [ ] , "地號" : [ ] , "門牌" : [ ] , "縣市別" : "台中市"} , { "_id" : { "$oid" : "60d1cff136f48c39416c85d6"} , "執照類別" : "建造執照" , "核發執照字號" : "82府都建建字第06608號" , "原領執照字號" : "" , "變更設計次數" : "00" , "基地面積" : "0㎡" , "建築面積" : "0㎡" , "總樓地板面積" : "0㎡" , "建築物高度" : "0ｍ" , "地下避難面積" : "0㎡" , "法定空地面積" : "0㎡" , "建造類別" : "" , "構造別" : "" , "地上層數" : "0層" , "地下層數" : "0層" , "棟數" : "0棟" , "戶數" : "0戶" , "起造人代表人" : "" , "起造人地址" : "" , "設計人" : "" , "監造人" : "" , "承造人" : "" , "雜項工作物" : "" , "停車空間" : "法定0輛，獎勵0輛，自設0輛" , "發照日期" : "年月日" , "實際開工日期" : "年月日" , "竣工日期" : "年月日" , "土地使用分區" : "" , "建築物用途" : "" , "工程造價" : "" , "qtime" : "" , "樓層概要" : [ ] , "地號" : [ ] , "門牌" : [ ] , "縣市別" : "台中市"} , { "_id" : { "$oid" : "60d1cff136f48c39416c85d7"} , "執照類別" : "建造執照" , "核發執照字號" : "82府都建建字第06609號" , "原領執照字號" : "" , "變更設計次數" : "00" , "基地面積" : "0㎡" , "建築面積" : "0㎡" , "總樓地板面積" : "0㎡" , "建築物高度" : "0ｍ" , "地下避難面積" : "0㎡" , "法定空地面積" : "0㎡" , "建造類別" : "" , "構造別" : "" , "地上層數" : "0層" , "地下層數" : "0層" , "棟數" : "0棟" , "戶數" : "0戶" , "起造人代表人" : "" , "起造人地址" : "" , "設計人" : "" , "監造人" : "" , "承造人" : "" , "雜項工作物" : "" , "停車空間" : "法定0輛，獎勵0輛，自設0輛" , "發照日期" : "年月日" , "實際開工日期" : "年月日" , "竣工日期" : "年月日" , "土地使用分區" : "" , "建築物用途" : "" , "工程造價" : "" , "qtime" : "" , "樓層概要" : [ ] , "地號" : [ ] , "門牌" : [ ] , "縣市別" : "台中市"} , { "_id" : { "$oid" : "60d1cff136f48c39416c85d8"} , "執照類別" : "建造執照" , "核發執照字號" : "82府都建建字第06611號" , "原領執照字號" : "" , "變更設計次數" : "00" , "基地面積" : "0㎡" , "建築面積" : "0㎡" , "總樓地板面積" : "0㎡" , "建築物高度" : "0ｍ" , "地下避難面積" : "0㎡" , "法定空地面積" : "0㎡" , "建造類別" : "" , "構造別" : "" , "地上層數" : "0層" , "地下層數" : "0層" , "棟數" : "0棟" , "戶數" : "0戶" , "起造人代表人" : "" , "起造人地址" : "" , "設計人" : "" , "監造人" : "" , "承造人" : "" , "雜項工作物" : "" , "停車空間" : "法定0輛，獎勵0輛，自設0輛" , "發照日期" : "年月日" , "實際開工日期" : "年月日" , "竣工日期" : "年月日" , "土地使用分區" : "" , "建築物用途" : "" , "工程造價" : "" , "qtime" : "" , "樓層概要" : [ ] , "地號" : [ ] , "門牌" : [ ] , "縣市別" : "台中市"} , { "_id" : { "$oid" : "60d1cff136f48c39416c85d9"} , "執照類別" : "建造執照" , "核發執照字號" : "82府都建建字第06615號" , "原領執照字號" : "" , "變更設計次數" : "00" , "基地面積" : "0㎡" , "建築面積" : "0㎡" , "總樓地板面積" : "0㎡" , "建築物高度" : "0ｍ" , "地下避難面積" : "0㎡" , "法定空地面積" : "0㎡" , "建造類別" : "" , "構造別" : "" , "地上層數" : "0層" , "地下層數" : "0層" , "棟數" : "0棟" , "戶數" : "0戶" , "起造人代表人" : "" , "起造人地址" : "" , "設計人" : "" , "監造人" : "" , "承造人" : "" , "雜項工作物" : "" , "停車空間" : "法定0輛，獎勵0輛，自設0輛" , "發照日期" : "年月日" , "實際開工日期" : "年月日" , "竣工日期" : "年月日" , "土地使用分區" : "" , "建築物用途" : "" , "工程造價" : "" , "qtime" : "" , "樓層概要" : [ ] , "地號" : [ ] , "門牌" : [ ] , "縣市別" : "台中市"} , { "_id" : { "$oid" : "60d1cff136f48c39416c85da"} , "執照類別" : "建造執照" , "核發執照字號" : "82府都建建字第06616號" , "原領執照字號" : "" , "變更設計次數" : "00" , "基地面積" : "0㎡" , "建築面積" : "0㎡" , "總樓地板面積" : "0㎡" , "建築物高度" : "0ｍ" , "地下避難面積" : "0㎡" , "法定空地面積" : "0㎡" , "建造類別" : "" , "構造別" : "" , "地上層數" : "0層" , "地下層數" : "0層" , "棟數" : "0棟" , "戶數" : "0戶" , "起造人代表人" : "" , "起造人地址" : "" , "設計人" : "" , "監造人" : "" , "承造人" : "" , "雜項工作物" : "" , "停車空間" : "法定0輛，獎勵0輛，自設0輛" , "發照日期" : "年月日" , "實際開工日期" : "年月日" , "竣工日期" : "年月日" , "土地使用分區" : "" , "建築物用途" : "" , "工程造價" : "" , "qtime" : "" , "樓層概要" : [ ] , "地號" : [ ] , "門牌" : [ ] , "縣市別" : "台中市"} , { "_id" : { "$oid" : "60d1cff136f48c39416c85db"} , "執照類別" : "建造執照" , "核發執照字號" : "82府都建建字第06617號" , "原領執照字號" : "" , "變更設計次數" : "00" , "基地面積" : "0㎡" , "建築面積" : "0㎡" , "總樓地板面積" : "0㎡" , "建築物高度" : "0ｍ" , "地下避難面積" : "0㎡" , "法定空地面積" : "0㎡" , "建造類別" : "" , "構造別" : "" , "地上層數" : "0層" , "地下層數" : "0層" , "棟數" : "0棟" , "戶數" : "0戶" , "起造人代表人" : "" , "起造人地址" : "" , "設計人" : "" , "監造人" : "" , "承造人" : "" , "雜項工作物" : "" , "停車空間" : "法定0輛，獎勵0輛，自設0輛" , "發照日期" : "年月日" , "實際開工日期" : "年月日" , "竣工日期" : "年月日" , "土地使用分區" : "" , "建築物用途" : "" , "工程造價" : "" , "qtime" : "" , "樓層概要" : [ ] , "地號" : [ ] , "門牌" : [ ] , "縣市別" : "台中市"} , { "_id" : { "$oid" : "60d1cff136f48c39416c85dc"} , "執照類別" : "建造執照" , "核發執照字號" : "82府都建建字第06618號" , "原領執照字號" : "" , "變更設計次數" : "00" , "基地面積" : "0㎡" , "建築面積" : "0㎡" , "總樓地板面積" : "0㎡" , "建築物高度" : "0ｍ" , "地下避難面積" : "0㎡" , "法定空地面積" : "0㎡" , "建造類別" : "" , "構造別" : "" , "地上層數" : "0層" , "地下層數" : "0層" , "棟數" : "0棟" , "戶數" : "0戶" , "起造人代表人" : "" , "起造人地址" : "" , "設計人" : "" , "監造人" : "" , "承造人" : "" , "雜項工作物" : "" , "停車空間" : "法定0輛，獎勵0輛，自設0輛" , "發照日期" : "年月日" , "實際開工日期" : "年月日" , "竣工日期" : "年月日" , "土地使用分區" : "" , "建築物用途" : "" , "工程造價" : "" , "qtime" : "" , "樓層概要" : [ ] , "地號" : [ ] , "門牌" : [ ] , "縣市別" : "台中市"} , { "_id" : { "$oid" : "60d1cff136f48c39416c85dd"} , "執照類別" : "建造執照" , "核發執照字號" : "82府都建建字第06619號" , "原領執照字號" : "" , "變更設計次數" : "00" , "基地面積" : "0㎡" , "建築面積" : "0㎡" , "總樓地板面積" : "0㎡" , "建築物高度" : "0ｍ" , "地下避難面積" : "0㎡" , "法定空地面積" : "0㎡" , "建造類別" : "" , "構造別" : "" , "地上層數" : "0層" , "地下層數" : "0層" , "棟數" : "0棟" , "戶數" : "0戶" , "起造人代表人" : "" , "起造人地址" : "" , "設計人" : "" , "監造人" : "" , "承造人" : "" , "雜項工作物" : "" , "停車空間" : "法定0輛，獎勵0輛，自設0輛" , "發照日期" : "年月日" , "實際開工日期" : "年月日" , "竣工日期" : "年月日" , "土地使用分區" : "" , "建築物用途" : "" , "工程造價" : "" , "qtime" : "" , "樓層概要" : [ ] , "地號" : [ ] , "門牌" : [ ] , "縣市別" : "台中市"} , { "_id" : { "$oid" : "60d1cff136f48c39416c85de"} , "執照類別" : "建造執照" , "核發執照字號" : "82府都建建字第06620號" , "原領執照字號" : "" , "變更設計次數" : "00" , "基地面積" : "0㎡" , "建築面積" : "0㎡" , "總樓地板面積" : "0㎡" , "建築物高度" : "0ｍ" , "地下避難面積" : "0㎡" , "法定空地面積" : "0㎡" , "建造類別" : "" , "構造別" : "" , "地上層數" : "0層" , "地下層數" : "0層" , "棟數" : "0棟" , "戶數" : "0戶" , "起造人代表人" : "" , "起造人地址" : "" , "設計人" : "" , "監造人" : "" , "承造人" : "" , "雜項工作物" : "" , "停車空間" : "法定0輛，獎勵0輛，自設0輛" , "發照日期" : "年月日" , "實際開工日期" : "年月日" , "竣工日期" : "年月日" , "土地使用分區" : "" , "建築物用途" : "" , "工程造價" : "" , "qtime" : "" , "樓層概要" : [ ] , "地號" : [ ] , "門牌" : [ ] , "縣市別" : "台中市"} , { "_id" : { "$oid" : "60d1cff136f48c39416c85df"} , "執照類別" : "建造執照" , "核發執照字號" : "83府都建建字第00082號" , "原領執照字號" : "" , "變更設計次數" : "00" , "基地面積" : "0㎡" , "建築面積" : "0㎡" , "總樓地板面積" : "0㎡" , "建築物高度" : "0ｍ" , "地下避難面積" : "0㎡" , "法定空地面積" : "0㎡" , "建造類別" : "" , "構造別" : "" , "地上層數" : "0層" , "地下層數" : "0層" , "棟數" : "0棟" , "戶數" : "0戶" , "起造人代表人" : "" , "起造人地址" : "" , "設計人" : "" , "監造人" : "" , "承造人" : "" , "雜項工作物" : "" , "停車空間" : "法定0輛，獎勵0輛，自設0輛" , "發照日期" : "年月日" , "實際開工日期" : "年月日" , "竣工日期" : "年月日" , "土地使用分區" : "" , "建築物用途" : "" , "工程造價" : "" , "qtime" : "" , "樓層概要" : [ ] , "地號" : [ ] , "門牌" : [ ] , "縣市別" : "台中市"} , { "_id" : { "$oid" : "60d1cff136f48c39416c85e0"} , "執照類別" : "建造執照" , "核發執照字號" : "83府都建建字第00091號" , "原領執照字號" : "" , "變更設計次數" : "00" , "基地面積" : "0㎡" , "建築面積" : "0㎡" , "總樓地板面積" : "0㎡" , "建築物高度" : "0ｍ" , "地下避難面積" : "0㎡" , "法定空地面積" : "0㎡" , "建造類別" : "" , "構造別" : "" , "地上層數" : "0層" , "地下層數" : "0層" , "棟數" : "0棟" , "戶數" : "0戶" , "起造人代表人" : "" , "起造人地址" : "" , "設計人" : "" , "監造人" : "" , "承造人" : "" , "雜項工作物" : "" , "停車空間" : "法定0輛，獎勵0輛，自設0輛" , "發照日期" : "年月日" , "實際開工日期" : "年月日" , "竣工日期" : "年月日" , "土地使用分區" : "" , "建築物用途" : "" , "工程造價" : "" , "qtime" : "" , "樓層概要" : [ ] , "地號" : [ ] , "門牌" : [ ] , "縣市別" : "台中市"} , { "_id" : { "$oid" : "60d1cff136f48c39416c85e1"} , "執照類別" : "建造執照" , "核發執照字號" : "83府都建建字第00092號" , "原領執照字號" : "" , "變更設計次數" : "00" , "基地面積" : "0㎡" , "建築面積" : "0㎡" , "總樓地板面積" : "0㎡" , "建築物高度" : "0ｍ" , "地下避難面積" : "0㎡" , "法定空地面積" : "0㎡" , "建造類別" : "" , "構造別" : "" , "地上層數" : "0層" , "地下層數" : "0層" , "棟數" : "0棟" , "戶數" : "0戶" , "起造人代表人" : "" , "起造人地址" : "" , "設計人" : "" , "監造人" : "" , "承造人" : "" , "雜項工作物" : "" , "停車空間" : "法定0輛，獎勵0輛，自設0輛" , "發照日期" : "年月日" , "實際開工日期" : "年月日" , "竣工日期" : "年月日" , "土地使用分區" : "" , "建築物用途" : "" , "工程造價" : "" , "qtime" : "" , "樓層概要" : [ ] , "地號" : [ ] , "門牌" : [ ] , "縣市別" : "台中市"} , { "_id" : { "$oid" : "60d1cff136f48c39416c85e2"} , "執照類別" : "建造執照" , "核發執照字號" : "83府都建建字第00093號" , "原領執照字號" : "" , "變更設計次數" : "00" , "基地面積" : "0㎡" , "建築面積" : "0㎡" , "總樓地板面積" : "0㎡" , "建築物高度" : "0ｍ" , "地下避難面積" : "0㎡" , "法定空地面積" : "0㎡" , "建造類別" : "" , "構造別" : "" , "地上層數" : "0層" , "地下層數" : "0層" , "棟數" : "0棟" , "戶數" : "0戶" , "起造人代表人" : "" , "起造人地址" : "" , "設計人" : "" , "監造人" : "" , "承造人" : "" , "雜項工作物" : "" , "停車空間" : "法定0輛，獎勵0輛，自設0輛" , "發照日期" : "年月日" , "實際開工日期" : "年月日" , "竣工日期" : "年月日" , "土地使用分區" : "" , "建築物用途" : "" , "工程造價" : "" , "qtime" : "" , "樓層概要" : [ ] , "地號" : [ ] , "門牌" : [ ] , "縣市別" : "台中市"} , { "_id" : { "$oid" : "60d1cff136f48c39416c85e3"} , "執照類別" : "建造執照" , "核發執照字號" : "(83)工建建字第00104號" , "原領執照字號" : "" , "變更設計次數" : "00" , "基地面積" : "0㎡" , "建築面積" : "0㎡" , "總樓地板面積" : "0㎡" , "建築物高度" : "0ｍ" , "地下避難面積" : "0㎡" , "法定空地面積" : "0㎡" , "建造類別" : "" , "構造別" : "" , "地上層數" : "0層" , "地下層數" : "0層" , "棟數" : "0棟" , "戶數" : "0戶" , "起造人代表人" : "" , "起造人地址" : "" , "設計人" : "" , "監造人" : "" , "承造人" : "" , "雜項工作物" : "" , "停車空間" : "法定0輛，獎勵0輛，自設0輛" , "發照日期" : "年月日" , "實際開工日期" : "年月日" , "竣工日期" : "年月日" , "土地使用分區" : "" , "建築物用途" : "" , "工程造價" : "" , "qtime" : "" , "樓層概要" : [ ] , "地號" : [ ] , "門牌" : [ ] , "縣市別" : "台中市"} , { "_id" : { "$oid" : "60d1cff136f48c39416c85e4"} , "執照類別" : "建造執照" , "核發執照字號" : "(83)工建建字第00105號" , "原領執照字號" : "" , "變更設計次數" : "00" , "基地面積" : "0㎡" , "建築面積" : "0㎡" , "總樓地板面積" : "0㎡" , "建築物高度" : "0ｍ" , "地下避難面積" : "0㎡" , "法定空地面積" : "0㎡" , "建造類別" : "" , "構造別" : "" , "地上層數" : "0層" , "地下層數" : "0層" , "棟數" : "0棟" , "戶數" : "0戶" , "起造人代表人" : "" , "起造人地址" : "" , "設計人" : "" , "監造人" : "" , "承造人" : "" , "雜項工作物" : "" , "停車空間" : "法定0輛，獎勵0輛，自設0輛" , "發照日期" : "年月日" , "實際開工日期" : "年月日" , "竣工日期" : "年月日" , "土地使用分區" : "" , "建築物用途" : "" , "工程造價" : "" , "qtime" : "" , "樓層概要" : [ ] , "地號" : [ ] , "門牌" : [ ] , "縣市別" : "台中市"} , { "_id" : { "$oid" : "60d1cff136f48c39416c85e5"} , "執照類別" : "建造執照" , "核發執照字號" : "(83)工建建字第00106號" , "原領執照字號" : "" , "變更設計次數" : "00" , "基地面積" : "0㎡" , "建築面積" : "0㎡" , "總樓地板面積" : "0㎡" , "建築物高度" : "0ｍ" , "地下避難面積" : "0㎡" , "法定空地面積" : "0㎡" , "建造類別" : "" , "構造別" : "" , "地上層數" : "0層" , "地下層數" : "0層" , "棟數" : "0棟" , "戶數" : "0戶" , "起造人代表人" : "" , "起造人地址" : "" , "設計人" : "" , "監造人" : "" , "承造人" : "" , "雜項工作物" : "" , "停車空間" : "法定0輛，獎勵0輛，自設0輛" , "發照日期" : "年月日" , "實際開工日期" : "年月日" , "竣工日期" : "年月日" , "土地使用分區" : "" , "建築物用途" : "" , "工程造價" : "" , "qtime" : "" , "樓層概要" : [ ] , "地號" : [ ] , "門牌" : [ ] , "縣市別" : "台中市"} , { "_id" : { "$oid" : "60d1cff136f48c39416c85e6"} , "執照類別" : "建造執照" , "核發執照字號" : "(83)工建建字第00107號" , "原領執照字號" : "" , "變更設計次數" : "00" , "基地面積" : "0㎡" , "建築面積" : "0㎡" , "總樓地板面積" : "0㎡" , "建築物高度" : "0ｍ" , "地下避難面積" : "0㎡" , "法定空地面積" : "0㎡" , "建造類別" : "" , "構造別" : "" , "地上層數" : "0層" , "地下層數" : "0層" , "棟數" : "0棟" , "戶數" : "0戶" , "起造人代表人" : "" , "起造人地址" : "" , "設計人" : "" , "監造人" : "" , "承造人" : "" , "雜項工作物" : "" , "停車空間" : "法定0輛，獎勵0輛，自設0輛" , "發照日期" : "年月日" , "實際開工日期" : "年月日" , "竣工日期" : "年月日" , "土地使用分區" : "" , "建築物用途" : "" , "工程造價" : "" , "qtime" : "" , "樓層概要" : [ ] , "地號" : [ ] , "門牌" : [ ] , "縣市別" : "台中市"} , { "_id" : { "$oid" : "60d1cff136f48c39416c85e7"} , "執照類別" : "建造執照" , "核發執照字號" : "(83)工建建字第00108號" , "原領執照字號" : "" , "變更設計次數" : "00" , "基地面積" : "0㎡" , "建築面積" : "0㎡" , "總樓地板面積" : "0㎡" , "建築物高度" : "0ｍ" , "地下避難面積" : "0㎡" , "法定空地面積" : "0㎡" , "建造類別" : "" , "構造別" : "" , "地上層數" : "0層" , "地下層數" : "0層" , "棟數" : "0棟" , "戶數" : "0戶" , "起造人代表人" : "" , "起造人地址" : "" , "設計人" : "" , "監造人" : "" , "承造人" : "" , "雜項工作物" : "" , "停車空間" : "法定0輛，獎勵0輛，自設0輛" , "發照日期" : "年月日" , "實際開工日期" : "年月日" , "竣工日期" : "年月日" , "土地使用分區" : "" , "建築物用途" : "" , "工程造價" : "" , "qtime" : "" , "樓層概要" : [ ] , "地號" : [ ] , "門牌" : [ ] , "縣市別" : "台中市"} , { "_id" : { "$oid" : "60d1cff136f48c39416c85e8"} , "執照類別" : "建造執照" , "核發執照字號" : "(83)工建建字第00109號" , "原領執照字號" : "" , "變更設計次數" : "00" , "基地面積" : "0㎡" , "建築面積" : "0㎡" , "總樓地板面積" : "0㎡" , "建築物高度" : "0ｍ" , "地下避難面積" : "0㎡" , "法定空地面積" : "0㎡" , "建造類別" : "" , "構造別" : "" , "地上層數" : "0層" , "地下層數" : "0層" , "棟數" : "0棟" , "戶數" : "0戶" , "起造人代表人" : "" , "起造人地址" : "" , "設計人" : "" , "監造人" : "" , "承造人" : "" , "雜項工作物" : "" , "停車空間" : "法定0輛，獎勵0輛，自設0輛" , "發照日期" : "年月日" , "實際開工日期" : "年月日" , "竣工日期" : "年月日" , "土地使用分區" : "" , "建築物用途" : "" , "工程造價" : "" , "qtime" : "" , "樓層概要" : [ ] , "地號" : [ ] , "門牌" : [ ] , "縣市別" : "台中市"} , { "_id" : { "$oid" : "60d1cff136f48c39416c85e9"} , "執照類別" : "建造執照" , "核發執照字號" : "(83)工建建字第00110號" , "原領執照字號" : "" , "變更設計次數" : "00" , "基地面積" : "0㎡" , "建築面積" : "0㎡" , "總樓地板面積" : "0㎡" , "建築物高度" : "0ｍ" , "地下避難面積" : "0㎡" , "法定空地面積" : "0㎡" , "建造類別" : "" , "構造別" : "" , "地上層數" : "0層" , "地下層數" : "0層" , "棟數" : "0棟" , "戶數" : "0戶" , "起造人代表人" : "" , "起造人地址" : "" , "設計人" : "" , "監造人" : "" , "承造人" : "" , "雜項工作物" : "" , "停車空間" : "法定0輛，獎勵0輛，自設0輛" , "發照日期" : "年月日" , "實際開工日期" : "年月日" , "竣工日期" : "年月日" , "土地使用分區" : "" , "建築物用途" : "" , "工程造價" : "" , "qtime" : "" , "樓層概要" : [ ] , "地號" : [ ] , "門牌" : [ ] , "縣市別" : "台中市"} , { "_id" : { "$oid" : "60d1cff136f48c39416c85ea"} , "執照類別" : "建造執照" , "核發執照字號" : "(83)工建建字第00111號" , "原領執照字號" : "" , "變更設計次數" : "00" , "基地面積" : "0㎡" , "建築面積" : "0㎡" , "總樓地板面積" : "0㎡" , "建築物高度" : "0ｍ" , "地下避難面積" : "0㎡" , "法定空地面積" : "0㎡" , "建造類別" : "" , "構造別" : "" , "地上層數" : "0層" , "地下層數" : "0層" , "棟數" : "0棟" , "戶數" : "0戶" , "起造人代表人" : "" , "起造人地址" : "" , "設計人" : "" , "監造人" : "" , "承造人" : "" , "雜項工作物" : "" , "停車空間" : "法定0輛，獎勵0輛，自設0輛" , "發照日期" : "年月日" , "實際開工日期" : "年月日" , "竣工日期" : "年月日" , "土地使用分區" : "" , "建築物用途" : "" , "工程造價" : "" , "qtime" : "" , "樓層概要" : [ ] , "地號" : [ ] , "門牌" : [ ] , "縣市別" : "台中市"} , { "_id" : { "$oid" : "60d1cff136f48c39416c85eb"} , "執照類別" : "建造執照" , "核發執照字號" : "(83)工建建字第00112號" , "原領執照字號" : "" , "變更設計次數" : "00" , "基地面積" : "0㎡" , "建築面積" : "0㎡" , "總樓地板面積" : "0㎡" , "建築物高度" : "0ｍ" , "地下避難面積" : "0㎡" , "法定空地面積" : "0㎡" , "建造類別" : "" , "構造別" : "" , "地上層數" : "0層" , "地下層數" : "0層" , "棟數" : "0棟" , "戶數" : "0戶" , "起造人代表人" : "" , "起造人地址" : "" , "設計人" : "" , "監造人" : "" , "承造人" : "" , "雜項工作物" : "" , "停車空間" : "法定0輛，獎勵0輛，自設0輛" , "發照日期" : "年月日" , "實際開工日期" : "年月日" , "竣工日期" : "年月日" , "土地使用分區" : "" , "建築物用途" : "" , "工程造價" : "" , "qtime" : "" , "樓層概要" : [ ] , "地號" : [ ] , "門牌" : [ ] , "縣市別" : "台中市"} , { "_id" : { "$oid" : "60d1cff136f48c39416c85ec"} , "執照類別" : "建造執照" , "核發執照字號" : "(83)工建建字第00113號" , "原領執照字號" : "" , "變更設計次數" : "00" , "基地面積" : "0㎡" , "建築面積" : "0㎡" , "總樓地板面積" : "0㎡" , "建築物高度" : "0ｍ" , "地下避難面積" : "0㎡" , "法定空地面積" : "0㎡" , "建造類別" : "" , "構造別" : "" , "地上層數" : "0層" , "地下層數" : "0層" , "棟數" : "0棟" , "戶數" : "0戶" , "起造人代表人" : "" , "起造人地址" : "" , "設計人" : "" , "監造人" : "" , "承造人" : "" , "雜項工作物" : "" , "停車空間" : "法定0輛，獎勵0輛，自設0輛" , "發照日期" : "年月日" , "實際開工日期" : "年月日" , "竣工日期" : "年月日" , "土地使用分區" : "" , "建築物用途" : "" , "工程造價" : "" , "qtime" : "" , "樓層概要" : [ ] , "地號" : [ ] , "門牌" : [ ] , "縣市別" : "台中市"} , { "_id" : { "$oid" : "60d1cff136f48c39416c85ed"} , "執照類別" : "建造執照" , "核發執照字號" : "(83)工建建字第00114號" , "原領執照字號" : "" , "變更設計次數" : "00" , "基地面積" : "0㎡" , "建築面積" : "0㎡" , "總樓地板面積" : "0㎡" , "建築物高度" : "0ｍ" , "地下避難面積" : "0㎡" , "法定空地面積" : "0㎡" , "建造類別" : "" , "構造別" : "" , "地上層數" : "0層" , "地下層數" : "0層" , "棟數" : "0棟" , "戶數" : "0戶" , "起造人代表人" : "" , "起造人地址" : "" , "設計人" : "" , "監造人" : "" , "承造人" : "" , "雜項工作物" : "" , "停車空間" : "法定0輛，獎勵0輛，自設0輛" , "發照日期" : "年月日" , "實際開工日期" : "年月日" , "竣工日期" : "年月日" , "土地使用分區" : "" , "建築物用途" : "" , "工程造價" : "" , "qtime" : "" , "樓層概要" : [ ] , "地號" : [ ] , "門牌" : [ ] , "縣市別" : "台中市"} , { "_id" : { "$oid" : "60d1cff136f48c39416c85ee"} , "執照類別" : "建造執照" , "核發執照字號" : "82府都建建字第06634號" , "原領執照字號" : "" , "變更設計次數" : "00" , "基地面積" : "0㎡" , "建築面積" : "0㎡" , "總樓地板面積" : "0㎡" , "建築物高度" : "0ｍ" , "地下避難面積" : "0㎡" , "法定空地面積" : "0㎡" , "建造類別" : "" , "構造別" : "" , "地上層數" : "0層" , "地下層數" : "0層" , "棟數" : "0棟" , "戶數" : "0戶" , "起造人代表人" : "" , "起造人地址" : "" , "設計人" : "" , "監造人" : "" , "承造人" : "" , "雜項工作物" : "" , "停車空間" : "法定0輛，獎勵0輛，自設0輛" , "發照日期" : "年月日" , "實際開工日期" : "年月日" , "竣工日期" : "年月日" , "土地使用分區" : "" , "建築物用途" : "" , "工程造價" : "" , "qtime" : "" , "樓層概要" : [ ] , "地號" : [ ] , "門牌" : [ ] , "縣市別" : "台中市"} , { "_id" : { "$oid" : "60d1cff136f48c39416c85ef"} , "執照類別" : "建造執照" , "核發執照字號" : "82府都建建字第06635號" , "原領執照字號" : "" , "變更設計次數" : "00" , "基地面積" : "0㎡" , "建築面積" : "0㎡" , "總樓地板面積" : "0㎡" , "建築物高度" : "0ｍ" , "地下避難面積" : "0㎡" , "法定空地面積" : "0㎡" , "建造類別" : "" , "構造別" : "" , "地上層數" : "0層" , "地下層數" : "0層" , "棟數" : "0棟" , "戶數" : "0戶" , "起造人代表人" : "" , "起造人地址" : "" , "設計人" : "" , "監造人" : "" , "承造人" : "" , "雜項工作物" : "" , "停車空間" : "法定0輛，獎勵0輛，自設0輛" , "發照日期" : "年月日" , "實際開工日期" : "年月日" , "竣工日期" : "年月日" , "土地使用分區" : "" , "建築物用途" : "" , "工程造價" : "" , "qtime" : "" , "樓層概要" : [ ] , "地號" : [ ] , "門牌" : [ ] , "縣市別" : "台中市"} , { "_id" : { "$oid" : "60d1cff136f48c39416c85f0"} , "執照類別" : "建造執照" , "核發執照字號" : "82府都建建字第06636號" , "原領執照字號" : "" , "變更設計次數" : "00" , "基地面積" : "0㎡" , "建築面積" : "0㎡" , "總樓地板面積" : "0㎡" , "建築物高度" : "0ｍ" , "地下避難面積" : "0㎡" , "法定空地面積" : "0㎡" , "建造類別" : "" , "構造別" : "" , "地上層數" : "0層" , "地下層數" : "0層" , "棟數" : "0棟" , "戶數" : "0戶" , "起造人代表人" : "" , "起造人地址" : "" , "設計人" : "" , "監造人" : "" , "承造人" : "" , "雜項工作物" : "" , "停車空間" : "法定0輛，獎勵0輛，自設0輛" , "發照日期" : "年月日" , "實際開工日期" : "年月日" , "竣工日期" : "年月日" , "土地使用分區" : "" , "建築物用途" : "" , "工程造價" : "" , "qtime" : "" , "樓層概要" : [ ] , "地號" : [ ] , "門牌" : [ ] , "縣市別" : "台中市"} , { "_id" : { "$oid" : "60d1cff136f48c39416c85f1"} , "執照類別" : "建造執照" , "核發執照字號" : "82府都建建字第06637號" , "原領執照字號" : "" , "變更設計次數" : "00" , "基地面積" : "0㎡" , "建築面積" : "0㎡" , "總樓地板面積" : "0㎡" , "建築物高度" : "0ｍ" , "地下避難面積" : "0㎡" , "法定空地面積" : "0㎡" , "建造類別" : "" , "構造別" : "" , "地上層數" : "0層" , "地下層數" : "0層" , "棟數" : "0棟" , "戶數" : "0戶" , "起造人代表人" : "" , "起造人地址" : "" , "設計人" : "" , "監造人" : "" , "承造人" : "" , "雜項工作物" : "" , "停車空間" : "法定0輛，獎勵0輛，自設0輛" , "發照日期" : "年月日" , "實際開工日期" : "年月日" , "竣工日期" : "年月日" , "土地使用分區" : "" , "建築物用途" : "" , "工程造價" : "" , "qtime" : "" , "樓層概要" : [ ] , "地號" : [ ] , "門牌" : [ ] , "縣市別" : "台中市"} , { "_id" : { "$oid" : "60d1cff136f48c39416c85f2"} , "執照類別" : "建造執照" , "核發執照字號" : "82府都建建字第06638號" , "原領執照字號" : "" , "變更設計次數" : "00" , "基地面積" : "0㎡" , "建築面積" : "0㎡" , "總樓地板面積" : "0㎡" , "建築物高度" : "0ｍ" , "地下避難面積" : "0㎡" , "法定空地面積" : "0㎡" , "建造類別" : "" , "構造別" : "" , "地上層數" : "0層" , "地下層數" : "0層" , "棟數" : "0棟" , "戶數" : "0戶" , "起造人代表人" : "" , "起造人地址" : "" , "設計人" : "" , "監造人" : "" , "承造人" : "" , "雜項工作物" : "" , "停車空間" : "法定0輛，獎勵0輛，自設0輛" , "發照日期" : "年月日" , "實際開工日期" : "年月日" , "竣工日期" : "年月日" , "土地使用分區" : "" , "建築物用途" : "" , "工程造價" : "" , "qtime" : "" , "樓層概要" : [ ] , "地號" : [ ] , "門牌" : [ ] , "縣市別" : "台中市"} , { "_id" : { "$oid" : "60d1cff136f48c39416c85f3"} , "執照類別" : "建造執照" , "核發執照字號" : "82府都建建字第06639號" , "原領執照字號" : "" , "變更設計次數" : "00" , "基地面積" : "0㎡" , "建築面積" : "0㎡" , "總樓地板面積" : "0㎡" , "建築物高度" : "0ｍ" , "地下避難面積" : "0㎡" , "法定空地面積" : "0㎡" , "建造類別" : "" , "構造別" : "" , "地上層數" : "0層" , "地下層數" : "0層" , "棟數" : "0棟" , "戶數" : "0戶" , "起造人代表人" : "" , "起造人地址" : "" , "設計人" : "" , "監造人" : "" , "承造人" : "" , "雜項工作物" : "" , "停車空間" : "法定0輛，獎勵0輛，自設0輛" , "發照日期" : "年月日" , "實際開工日期" : "年月日" , "竣工日期" : "年月日" , "土地使用分區" : "" , "建築物用途" : "" , "工程造價" : "" , "qtime" : "" , "樓層概要" : [ ] , "地號" : [ ] , "門牌" : [ ] , "縣市別" : "台中市"} , { "_id" : { "$oid" : "60d1cff136f48c39416c85f4"} , "執照類別" : "建造執照" , "核發執照字號" : "82府都建建字第06640號" , "原領執照字號" : "" , "變更設計次數" : "00" , "基地面積" : "0㎡" , "建築面積" : "0㎡" , "總樓地板面積" : "0㎡" , "建築物高度" : "0ｍ" , "地下避難面積" : "0㎡" , "法定空地面積" : "0㎡" , "建造類別" : "" , "構造別" : "" , "地上層數" : "0層" , "地下層數" : "0層" , "棟數" : "0棟" , "戶數" : "0戶" , "起造人代表人" : "" , "起造人地址" : "" , "設計人" : "" , "監造人" : "" , "承造人" : "" , "雜項工作物" : "" , "停車空間" : "法定0輛，獎勵0輛，自設0輛" , "發照日期" : "年月日" , "實際開工日期" : "年月日" , "竣工日期" : "年月日" , "土地使用分區" : "" , "建築物用途" : "" , "工程造價" : "" , "qtime" : "" , "樓層概要" : [ ] , "地號" : [ ] , "門牌" : [ ] , "縣市別" : "台中市"} , { "_id" : { "$oid" : "60d1cff136f48c39416c85f5"} , "執照類別" : "建造執照" , "核發執照字號" : "82府都建建字第06642號" , "原領執照字號" : "" , "變更設計次數" : "00" , "基地面積" : "0㎡" , "建築面積" : "0㎡" , "總樓地板面積" : "0㎡" , "建築物高度" : "0ｍ" , "地下避難面積" : "0㎡" , "法定空地面積" : "0㎡" , "建造類別" : "" , "構造別" : "" , "地上層數" : "0層" , "地下層數" : "0層" , "棟數" : "0棟" , "戶數" : "0戶" , "起造人代表人" : "" , "起造人地址" : "" , "設計人" : "" , "監造人" : "" , "承造人" : "" , "雜項工作物" : "" , "停車空間" : "法定0輛，獎勵0輛，自設0輛" , "發照日期" : "年月日" , "實際開工日期" : "年月日" , "竣工日期" : "年月日" , "土地使用分區" : "" , "建築物用途" : "" , "工程造價" : "" , "qtime" : "" , "樓層概要" : [ ] , "地號" : [ ] , "門牌" : [ ] , "縣市別" : "台中市"} , { "_id" : { "$oid" : "60d1cff136f48c39416c85f6"} , "執照類別" : "建造執照" , "核發執照字號" : "82府都建建字第06643號" , "原領執照字號" : "" , "變更設計次數" : "00" , "基地面積" : "0㎡" , "建築面積" : "0㎡" , "總樓地板面積" : "0㎡" , "建築物高度" : "0ｍ" , "地下避難面積" : "0㎡" , "法定空地面積" : "0㎡" , "建造類別" : "" , "構造別" : "" , "地上層數" : "0層" , "地下層數" : "0層" , "棟數" : "0棟" , "戶數" : "0戶" , "起造人代表人" : "" , "起造人地址" : "" , "設計人" : "" , "監造人" : "" , "承造人" : "" , "雜項工作物" : "" , "停車空間" : "法定0輛，獎勵0輛，自設0輛" , "發照日期" : "年月日" , "實際開工日期" : "年月日" , "竣工日期" : "年月日" , "土地使用分區" : "" , "建築物用途" : "" , "工程造價" : "" , "qtime" : "" , "樓層概要" : [ ] , "地號" : [ ] , "門牌" : [ ] , "縣市別" : "台中市"} , { "_id" : { "$oid" : "60d1cff136f48c39416c85f7"} , "執照類別" : "建造執照" , "核發執照字號" : "82府都建建字第06644號" , "原領執照字號" : "" , "變更設計次數" : "00" , "基地面積" : "0㎡" , "建築面積" : "0㎡" , "總樓地板面積" : "0㎡" , "建築物高度" : "0ｍ" , "地下避難面積" : "0㎡" , "法定空地面積" : "0㎡" , "建造類別" : "" , "構造別" : "" , "地上層數" : "0層" , "地下層數" : "0層" , "棟數" : "0棟" , "戶數" : "0戶" , "起造人代表人" : "" , "起造人地址" : "" , "設計人" : "" , "監造人" : "" , "承造人" : "" , "雜項工作物" : "" , "停車空間" : "法定0輛，獎勵0輛，自設0輛" , "發照日期" : "年月日" , "實際開工日期" : "年月日" , "竣工日期" : "年月日" , "土地使用分區" : "" , "建築物用途" : "" , "工程造價" : "" , "qtime" : "" , "樓層概要" : [ ] , "地號" : [ ] , "門牌" : [ ] , "縣市別" : "台中市"} , { "_id" : { "$oid" : "60d1cff136f48c39416c85f8"} , "執照類別" : "建造執照" , "核發執照字號" : "82府都建建字第06645號" , "原領執照字號" : "" , "變更設計次數" : "00" , "基地面積" : "0㎡" , "建築面積" : "0㎡" , "總樓地板面積" : "0㎡" , "建築物高度" : "0ｍ" , "地下避難面積" : "0㎡" , "法定空地面積" : "0㎡" , "建造類別" : "" , "構造別" : "" , "地上層數" : "0層" , "地下層數" : "0層" , "棟數" : "0棟" , "戶數" : "0戶" , "起造人代表人" : "" , "起造人地址" : "" , "設計人" : "" , "監造人" : "" , "承造人" : "" , "雜項工作物" : "" , "停車空間" : "法定0輛，獎勵0輛，自設0輛" , "發照日期" : "年月日" , "實際開工日期" : "年月日" , "竣工日期" : "年月日" , "土地使用分區" : "" , "建築物用途" : "" , "工程造價" : "" , "qtime" : "" , "樓層概要" : [ ] , "地號" : [ ] , "門牌" : [ ] , "縣市別" : "台中市"} , { "_id" : { "$oid" : "60d1cff136f48c39416c85f9"} , "執照類別" : "建造執照" , "核發執照字號" : "82府都建建字第06646號" , "原領執照字號" : "" , "變更設計次數" : "00" , "基地面積" : "0㎡" , "建築面積" : "0㎡" , "總樓地板面積" : "0㎡" , "建築物高度" : "0ｍ" , "地下避難面積" : "0㎡" , "法定空地面積" : "0㎡" , "建造類別" : "" , "構造別" : "" , "地上層數" : "0層" , "地下層數" : "0層" , "棟數" : "0棟" , "戶數" : "0戶" , "起造人代表人" : "" , "起造人地址" : "" , "設計人" : "" , "監造人" : "" , "承造人" : "" , "雜項工作物" : "" , "停車空間" : "法定0輛，獎勵0輛，自設0輛" , "發照日期" : "年月日" , "實際開工日期" : "年月日" , "竣工日期" : "年月日" , "土地使用分區" : "" , "建築物用途" : "" , "工程造價" : "" , "qtime" : "" , "樓層概要" : [ ] , "地號" : [ ] , "門牌" : [ ] , "縣市別" : "台中市"} , { "_id" : { "$oid" : "60d1cff136f48c39416c85fa"} , "執照類別" : "建造執照" , "核發執照字號" : "82府都建建字第06647號" , "原領執照字號" : "" , "變更設計次數" : "00" , "基地面積" : "0㎡" , "建築面積" : "0㎡" , "總樓地板面積" : "0㎡" , "建築物高度" : "0ｍ" , "地下避難面積" : "0㎡" , "法定空地面積" : "0㎡" , "建造類別" : "" , "構造別" : "" , "地上層數" : "0層" , "地下層數" : "0層" , "棟數" : "0棟" , "戶數" : "0戶" , "起造人代表人" : "" , "起造人地址" : "" , "設計人" : "" , "監造人" : "" , "承造人" : "" , "雜項工作物" : "" , "停車空間" : "法定0輛，獎勵0輛，自設0輛" , "發照日期" : "年月日" , "實際開工日期" : "年月日" , "竣工日期" : "年月日" , "土地使用分區" : "" , "建築物用途" : "" , "工程造價" : "" , "qtime" : "" , "樓層概要" : [ ] , "地號" : [ ] , "門牌" : [ ] , "縣市別" : "台中市"} , { "_id" : { "$oid" : "60d1cff136f48c39416c85fb"} , "執照類別" : "建造執照" , "核發執照字號" : "82府都建建字第06649號" , "原領執照字號" : "" , "變更設計次數" : "00" , "基地面積" : "0㎡" , "建築面積" : "0㎡" , "總樓地板面積" : "0㎡" , "建築物高度" : "0ｍ" , "地下避難面積" : "0㎡" , "法定空地面積" : "0㎡" , "建造類別" : "" , "構造別" : "" , "地上層數" : "0層" , "地下層數" : "0層" , "棟數" : "0棟" , "戶數" : "0戶" , "起造人代表人" : "" , "起造人地址" : "" , "設計人" : "" , "監造人" : "" , "承造人" : "" , "雜項工作物" : "" , "停車空間" : "法定0輛，獎勵0輛，自設0輛" , "發照日期" : "年月日" , "實際開工日期" : "年月日" , "竣工日期" : "年月日" , "土地使用分區" : "" , "建築物用途" : "" , "工程造價" : "" , "qtime" : "" , "樓層概要" : [ ] , "地號" : [ ] , "門牌" : [ ] , "縣市別" : "台中市"} , { "_id" : { "$oid" : "60d1cff136f48c39416c85fc"} , "執照類別" : "建造執照" , "核發執照字號" : "82府都建建字第06650號" , "原領執照字號" : "" , "變更設計次數" : "00" , "基地面積" : "0㎡" , "建築面積" : "0㎡" , "總樓地板面積" : "0㎡" , "建築物高度" : "0ｍ" , "地下避難面積" : "0㎡" , "法定空地面積" : "0㎡" , "建造類別" : "" , "構造別" : "" , "地上層數" : "0層" , "地下層數" : "0層" , "棟數" : "0棟" , "戶數" : "0戶" , "起造人代表人" : "" , "起造人地址" : "" , "設計人" : "" , "監造人" : "" , "承造人" : "" , "雜項工作物" : "" , "停車空間" : "法定0輛，獎勵0輛，自設0輛" , "發照日期" : "年月日" , "實際開工日期" : "年月日" , "竣工日期" : "年月日" , "土地使用分區" : "" , "建築物用途" : "" , "工程造價" : "" , "qtime" : "" , "樓層概要" : [ ] , "地號" : [ ] , "門牌" : [ ] , "縣市別" : "台中市"} , { "_id" : { "$oid" : "60d1cff136f48c39416c85fd"} , "執照類別" : "建造執照" , "核發執照字號" : "82府都建建字第06651號" , "原領執照字號" : "" , "變更設計次數" : "00" , "基地面積" : "0㎡" , "建築面積" : "0㎡" , "總樓地板面積" : "0㎡" , "建築物高度" : "0ｍ" , "地下避難面積" : "0㎡" , "法定空地面積" : "0㎡" , "建造類別" : "" , "構造別" : "" , "地上層數" : "0層" , "地下層數" : "0層" , "棟數" : "0棟" , "戶數" : "0戶" , "起造人代表人" : "" , "起造人地址" : "" , "設計人" : "" , "監造人" : "" , "承造人" : "" , "雜項工作物" : "" , "停車空間" : "法定0輛，獎勵0輛，自設0輛" , "發照日期" : "年月日" , "實際開工日期" : "年月日" , "竣工日期" : "年月日" , "土地使用分區" : "" , "建築物用途" : "" , "工程造價" : "" , "qtime" : "" , "樓層概要" : [ ] , "地號" : [ ] , "門牌" : [ ] , "縣市別" : "台中市"} , { "_id" : { "$oid" : "60d1cff136f48c39416c85fe"} , "執照類別" : "建造執照" , "核發執照字號" : "82府都建建字第06653號" , "原領執照字號" : "" , "變更設計次數" : "00" , "基地面積" : "0㎡" , "建築面積" : "0㎡" , "總樓地板面積" : "0㎡" , "建築物高度" : "0ｍ" , "地下避難面積" : "0㎡" , "法定空地面積" : "0㎡" , "建造類別" : "" , "構造別" : "" , "地上層數" : "0層" , "地下層數" : "0層" , "棟數" : "0棟" , "戶數" : "0戶" , "起造人代表人" : "" , "起造人地址" : "" , "設計人" : "" , "監造人" : "" , "承造人" : "" , "雜項工作物" : "" , "停車空間" : "法定0輛，獎勵0輛，自設0輛" , "發照日期" : "年月日" , "實際開工日期" : "年月日" , "竣工日期" : "年月日" , "土地使用分區" : "" , "建築物用途" : "" , "工程造價" : "" , "qtime" : "" , "樓層概要" : [ ] , "地號" : [ ] , "門牌" : [ ] , "縣市別" : "台中市"} , { "_id" : { "$oid" : "60d1cff136f48c39416c85ff"} , "執照類別" : "建造執照" , "核發執照字號" : "82府都建建字第06654號" , "原領執照字號" : "" , "變更設計次數" : "00" , "基地面積" : "0㎡" , "建築面積" : "0㎡" , "總樓地板面積" : "0㎡" , "建築物高度" : "0ｍ" , "地下避難面積" : "0㎡" , "法定空地面積" : "0㎡" , "建造類別" : "" , "構造別" : "" , "地上層數" : "0層" , "地下層數" : "0層" , "棟數" : "0棟" , "戶數" : "0戶" , "起造人代表人" : "" , "起造人地址" : "" , "設計人" : "" , "監造人" : "" , "承造人" : "" , "雜項工作物" : "" , "停車空間" : "法定0輛，獎勵0輛，自設0輛" , "發照日期" : "年月日" , "實際開工日期" : "年月日" , "竣工日期" : "年月日" , "土地使用分區" : "" , "建築物用途" : "" , "工程造價" : "" , "qtime" : "" , "樓層概要" : [ ] , "地號" : [ ] , "門牌" : [ ] , "縣市別" : "台中市"} , { "_id" : { "$oid" : "60d1cff136f48c39416c8600"} , "執照類別" : "建造執照" , "核發執照字號" : "82府都建建字第06655號" , "原領執照字號" : "" , "變更設計次數" : "00" , "基地面積" : "0㎡" , "建築面積" : "0㎡" , "總樓地板面積" : "0㎡" , "建築物高度" : "0ｍ" , "地下避難面積" : "0㎡" , "法定空地面積" : "0㎡" , "建造類別" : "" , "構造別" : "" , "地上層數" : "0層" , "地下層數" : "0層" , "棟數" : "0棟" , "戶數" : "0戶" , "起造人代表人" : "" , "起造人地址" : "" , "設計人" : "" , "監造人" : "" , "承造人" : "" , "雜項工作物" : "" , "停車空間" : "法定0輛，獎勵0輛，自設0輛" , "發照日期" : "年月日" , "實際開工日期" : "年月日" , "竣工日期" : "年月日" , "土地使用分區" : "" , "建築物用途" : "" , "工程造價" : "" , "qtime" : "" , "樓層概要" : [ ] , "地號" : [ ] , "門牌" : [ ] , "縣市別" : "台中市"} , { "_id" : { "$oid" : "60d1cff136f48c39416c8601"} , "執照類別" : "建造執照" , "核發執照字號" : "82府都建建字第06656號" , "原領執照字號" : "" , "變更設計次數" : "00" , "基地面積" : "0㎡" , "建築面積" : "0㎡" , "總樓地板面積" : "0㎡" , "建築物高度" : "0ｍ" , "地下避難面積" : "0㎡" , "法定空地面積" : "0㎡" , "建造類別" : "" , "構造別" : "" , "地上層數" : "0層" , "地下層數" : "0層" , "棟數" : "0棟" , "戶數" : "0戶" , "起造人代表人" : "" , "起造人地址" : "" , "設計人" : "" , "監造人" : "" , "承造人" : "" , "雜項工作物" : "" , "停車空間" : "法定0輛，獎勵0輛，自設0輛" , "發照日期" : "年月日" , "實際開工日期" : "年月日" , "竣工日期" : "年月日" , "土地使用分區" : "" , "建築物用途" : "" , "工程造價" : "" , "qtime" : "" , "樓層概要" : [ ] , "地號" : [ ] , "門牌" : [ ] , "縣市別" : "台中市"} , { "_id" : { "$oid" : "60d1cff136f48c39416c8602"} , "執照類別" : "建造執照" , "核發執照字號" : "82府都建建字第06657號" , "原領執照字號" : "" , "變更設計次數" : "00" , "基地面積" : "0㎡" , "建築面積" : "0㎡" , "總樓地板面積" : "0㎡" , "建築物高度" : "0ｍ" , "地下避難面積" : "0㎡" , "法定空地面積" : "0㎡" , "建造類別" : "" , "構造別" : "" , "地上層數" : "0層" , "地下層數" : "0層" , "棟數" : "0棟" , "戶數" : "0戶" , "起造人代表人" : "" , "起造人地址" : "" , "設計人" : "" , "監造人" : "" , "承造人" : "" , "雜項工作物" : "" , "停車空間" : "法定0輛，獎勵0輛，自設0輛" , "發照日期" : "年月日" , "實際開工日期" : "年月日" , "竣工日期" : "年月日" , "土地使用分區" : "" , "建築物用途" : "" , "工程造價" : "" , "qtime" : "" , "樓層概要" : [ ] , "地號" : [ ] , "門牌" : [ ] , "縣市別" : "台中市"} , { "_id" : { "$oid" : "60d1cff136f48c39416c8603"} , "執照類別" : "建造執照" , "核發執照字號" : "82府都建建字第06658號" , "原領執照字號" : "" , "變更設計次數" : "00" , "基地面積" : "0㎡" , "建築面積" : "0㎡" , "總樓地板面積" : "0㎡" , "建築物高度" : "0ｍ" , "地下避難面積" : "0㎡" , "法定空地面積" : "0㎡" , "建造類別" : "" , "構造別" : "" , "地上層數" : "0層" , "地下層數" : "0層" , "棟數" : "0棟" , "戶數" : "0戶" , "起造人代表人" : "" , "起造人地址" : "" , "設計人" : "" , "監造人" : "" , "承造人" : "" , "雜項工作物" : "" , "停車空間" : "法定0輛，獎勵0輛，自設0輛" , "發照日期" : "年月日" , "實際開工日期" : "年月日" , "竣工日期" : "年月日" , "土地使用分區" : "" , "建築物用途" : "" , "工程造價" : "" , "qtime" : "" , "樓層概要" : [ ] , "地號" : [ ] , "門牌" : [ ] , "縣市別" : "台中市"} , { "_id" : { "$oid" : "60d1cff136f48c39416c8604"} , "執照類別" : "建造執照" , "核發執照字號" : "82府都建建字第06660號" , "原領執照字號" : "" , "變更設計次數" : "00" , "基地面積" : "0㎡" , "建築面積" : "0㎡" , "總樓地板面積" : "0㎡" , "建築物高度" : "0ｍ" , "地下避難面積" : "0㎡" , "法定空地面積" : "0㎡" , "建造類別" : "" , "構造別" : "" , "地上層數" : "0層" , "地下層數" : "0層" , "棟數" : "0棟" , "戶數" : "0戶" , "起造人代表人" : "" , "起造人地址" : "" , "設計人" : "" , "監造人" : "" , "承造人" : "" , "雜項工作物" : "" , "停車空間" : "法定0輛，獎勵0輛，自設0輛" , "發照日期" : "年月日" , "實際開工日期" : "年月日" , "竣工日期" : "年月日" , "土地使用分區" : "" , "建築物用途" : "" , "工程造價" : "" , "qtime" : "" , "樓層概要" : [ ] , "地號" : [ ] , "門牌" : [ ] , "縣市別" : "台中市"} , { "_id" : { "$oid" : "60d1cff136f48c39416c8605"} , "執照類別" : "建造執照" , "核發執照字號" : "82府都建建字第06662號" , "原領執照字號" : "" , "變更設計次數" : "00" , "基地面積" : "0㎡" , "建築面積" : "0㎡" , "總樓地板面積" : "0㎡" , "建築物高度" : "0ｍ" , "地下避難面積" : "0㎡" , "法定空地面積" : "0㎡" , "建造類別" : "" , "構造別" : "" , "地上層數" : "0層" , "地下層數" : "0層" , "棟數" : "0棟" , "戶數" : "0戶" , "起造人代表人" : "" , "起造人地址" : "" , "設計人" : "" , "監造人" : "" , "承造人" : "" , "雜項工作物" : "" , "停車空間" : "法定0輛，獎勵0輛，自設0輛" , "發照日期" : "年月日" , "實際開工日期" : "年月日" , "竣工日期" : "年月日" , "土地使用分區" : "" , "建築物用途" : "" , "工程造價" : "" , "qtime" : "" , "樓層概要" : [ ] , "地號" : [ ] , "門牌" : [ ] , "縣市別" : "台中市"} , { "_id" : { "$oid" : "60d1cff136f48c39416c8606"} , "執照類別" : "建造執照" , "核發執照字號" : "82府都建建字第06663號" , "原領執照字號" : "" , "變更設計次數" : "00" , "基地面積" : "0㎡" , "建築面積" : "0㎡" , "總樓地板面積" : "0㎡" , "建築物高度" : "0ｍ" , "地下避難面積" : "0㎡" , "法定空地面積" : "0㎡" , "建造類別" : "" , "構造別" : "" , "地上層數" : "0層" , "地下層數" : "0層" , "棟數" : "0棟" , "戶數" : "0戶" , "起造人代表人" : "" , "起造人地址" : "" , "設計人" : "" , "監造人" : "" , "承造人" : "" , "雜項工作物" : "" , "停車空間" : "法定0輛，獎勵0輛，自設0輛" , "發照日期" : "年月日" , "實際開工日期" : "年月日" , "竣工日期" : "年月日" , "土地使用分區" : "" , "建築物用途" : "" , "工程造價" : "" , "qtime" : "" , "樓層概要" : [ ] , "地號" : [ ] , "門牌" : [ ] , "縣市別" : "台中市"} , { "_id" : { "$oid" : "60d1cff136f48c39416c8607"} , "執照類別" : "建造執照" , "核發執照字號" : "(83)工建建字第00152號" , "原領執照字號" : "" , "變更設計次數" : "00" , "基地面積" : "0㎡" , "建築面積" : "0㎡" , "總樓地板面積" : "0㎡" , "建築物高度" : "0ｍ" , "地下避難面積" : "0㎡" , "法定空地面積" : "0㎡" , "建造類別" : "" , "構造別" : "" , "地上層數" : "0層" , "地下層數" : "0層" , "棟數" : "0棟" , "戶數" : "0戶" , "起造人代表人" : "" , "起造人地址" : "" , "設計人" : "" , "監造人" : "" , "承造人" : "" , "雜項工作物" : "" , "停車空間" : "法定0輛，獎勵0輛，自設0輛" , "發照日期" : "年月日" , "實際開工日期" : "年月日" , "竣工日期" : "年月日" , "土地使用分區" : "" , "建築物用途" : "" , "工程造價" : "" , "qtime" : "" , "樓層概要" : [ ] , "地號" : [ ] , "門牌" : [ ] , "縣市別" : "台中市"} , { "_id" : { "$oid" : "60d1cff136f48c39416c8608"} , "執照類別" : "建造執照" , "核發執照字號" : "(83)工建建字第00153號" , "原領執照字號" : "" , "變更設計次數" : "00" , "基地面積" : "0㎡" , "建築面積" : "0㎡" , "總樓地板面積" : "0㎡" , "建築物高度" : "0ｍ" , "地下避難面積" : "0㎡" , "法定空地面積" : "0㎡" , "建造類別" : "" , "構造別" : "" , "地上層數" : "0層" , "地下層數" : "0層" , "棟數" : "0棟" , "戶數" : "0戶" , "起造人代表人" : "" , "起造人地址" : "" , "設計人" : "" , "監造人" : "" , "承造人" : "" , "雜項工作物" : "" , "停車空間" : "法定0輛，獎勵0輛，自設0輛" , "發照日期" : "年月日" , "實際開工日期" : "年月日" , "竣工日期" : "年月日" , "土地使用分區" : "" , "建築物用途" : "" , "工程造價" : "" , "qtime" : "" , "樓層概要" : [ ] , "地號" : [ ] , "門牌" : [ ] , "縣市別" : "台中市"} , { "_id" : { "$oid" : "60d1cff136f48c39416c8609"} , "執照類別" : "建造執照" , "核發執照字號" : "(83)工建建字第00154號" , "原領執照字號" : "" , "變更設計次數" : "00" , "基地面積" : "0㎡" , "建築面積" : "0㎡" , "總樓地板面積" : "0㎡" , "建築物高度" : "0ｍ" , "地下避難面積" : "0㎡" , "法定空地面積" : "0㎡" , "建造類別" : "" , "構造別" : "" , "地上層數" : "0層" , "地下層數" : "0層" , "棟數" : "0棟" , "戶數" : "0戶" , "起造人代表人" : "" , "起造人地址" : "" , "設計人" : "" , "監造人" : "" , "承造人" : "" , "雜項工作物" : "" , "停車空間" : "法定0輛，獎勵0輛，自設0輛" , "發照日期" : "年月日" , "實際開工日期" : "年月日" , "竣工日期" : "年月日" , "土地使用分區" : "" , "建築物用途" : "" , "工程造價" : "" , "qtime" : "" , "樓層概要" : [ ] , "地號" : [ ] , "門牌" : [ ] , "縣市別" : "台中市"} , { "_id" : { "$oid" : "60d1cff136f48c39416c860a"} , "執照類別" : "建造執照" , "核發執照字號" : "(83)工建建字第00155號" , "原領執照字號" : "" , "變更設計次數" : "00" , "基地面積" : "0㎡" , "建築面積" : "0㎡" , "總樓地板面積" : "0㎡" , "建築物高度" : "0ｍ" , "地下避難面積" : "0㎡" , "法定空地面積" : "0㎡" , "建造類別" : "" , "構造別" : "" , "地上層數" : "0層" , "地下層數" : "0層" , "棟數" : "0棟" , "戶數" : "0戶" , "起造人代表人" : "" , "起造人地址" : "" , "設計人" : "" , "監造人" : "" , "承造人" : "" , "雜項工作物" : "" , "停車空間" : "法定0輛，獎勵0輛，自設0輛" , "發照日期" : "年月日" , "實際開工日期" : "年月日" , "竣工日期" : "年月日" , "土地使用分區" : "" , "建築物用途" : "" , "工程造價" : "" , "qtime" : "" , "樓層概要" : [ ] , "地號" : [ ] , "門牌" : [ ] , "縣市別" : "台中市"} , { "_id" : { "$oid" : "60d1cff136f48c39416c860b"} , "執照類別" : "建造執照" , "核發執照字號" : "(83)工建建字第00156號" , "原領執照字號" : "" , "變更設計次數" : "00" , "基地面積" : "0㎡" , "建築面積" : "0㎡" , "總樓地板面積" : "0㎡" , "建築物高度" : "0ｍ" , "地下避難面積" : "0㎡" , "法定空地面積" : "0㎡" , "建造類別" : "" , "構造別" : "" , "地上層數" : "0層" , "地下層數" : "0層" , "棟數" : "0棟" , "戶數" : "0戶" , "起造人代表人" : "" , "起造人地址" : "" , "設計人" : "" , "監造人" : "" , "承造人" : "" , "雜項工作物" : "" , "停車空間" : "法定0輛，獎勵0輛，自設0輛" , "發照日期" : "年月日" , "實際開工日期" : "年月日" , "竣工日期" : "年月日" , "土地使用分區" : "" , "建築物用途" : "" , "工程造價" : "" , "qtime" : "" , "樓層概要" : [ ] , "地號" : [ ] , "門牌" : [ ] , "縣市別" : "台中市"} , { "_id" : { "$oid" : "60d1cff136f48c39416c860c"} , "執照類別" : "建造執照" , "核發執照字號" : "(83)工建建字第00157號" , "原領執照字號" : "" , "變更設計次數" : "00" , "基地面積" : "0㎡" , "建築面積" : "0㎡" , "總樓地板面積" : "0㎡" , "建築物高度" : "0ｍ" , "地下避難面積" : "0㎡" , "法定空地面積" : "0㎡" , "建造類別" : "" , "構造別" : "" , "地上層數" : "0層" , "地下層數" : "0層" , "棟數" : "0棟" , "戶數" : "0戶" , "起造人代表人" : "" , "起造人地址" : "" , "設計人" : "" , "監造人" : "" , "承造人" : "" , "雜項工作物" : "" , "停車空間" : "法定0輛，獎勵0輛，自設0輛" , "發照日期" : "年月日" , "實際開工日期" : "年月日" , "竣工日期" : "年月日" , "土地使用分區" : "" , "建築物用途" : "" , "工程造價" : "" , "qtime" : "" , "樓層概要" : [ ] , "地號" : [ ] , "門牌" : [ ] , "縣市別" : "台中市"} , { "_id" : { "$oid" : "60d1cff136f48c39416c860d"} , "執照類別" : "建造執照" , "核發執照字號" : "(83)工建建字第00158號" , "原領執照字號" : "" , "變更設計次數" : "00" , "基地面積" : "0㎡" , "建築面積" : "0㎡" , "總樓地板面積" : "0㎡" , "建築物高度" : "0ｍ" , "地下避難面積" : "0㎡" , "法定空地面積" : "0㎡" , "建造類別" : "" , "構造別" : "" , "地上層數" : "0層" , "地下層數" : "0層" , "棟數" : "0棟" , "戶數" : "0戶" , "起造人代表人" : "" , "起造人地址" : "" , "設計人" : "" , "監造人" : "" , "承造人" : "" , "雜項工作物" : "" , "停車空間" : "法定0輛，獎勵0輛，自設0輛" , "發照日期" : "年月日" , "實際開工日期" : "年月日" , "竣工日期" : "年月日" , "土地使用分區" : "" , "建築物用途" : "" , "工程造價" : "" , "qtime" : "" , "樓層概要" : [ ] , "地號" : [ ] , "門牌" : [ ] , "縣市別" : "台中市"} , { "_id" : { "$oid" : "60d1cff136f48c39416c860e"} , "執照類別" : "建造執照" , "核發執照字號" : "82府都建建字第06235號" , "原領執照字號" : "" , "變更設計次數" : "00" , "基地面積" : "0㎡" , "建築面積" : "0㎡" , "總樓地板面積" : "0㎡" , "建築物高度" : "0ｍ" , "地下避難面積" : "0㎡" , "法定空地面積" : "0㎡" , "建造類別" : "" , "構造別" : "" , "地上層數" : "0層" , "地下層數" : "0層" , "棟數" : "0棟" , "戶數" : "0戶" , "起造人代表人" : "" , "起造人地址" : "" , "設計人" : "" , "監造人" : "" , "承造人" : "" , "雜項工作物" : "" , "停車空間" : "法定0輛，獎勵0輛，自設0輛" , "發照日期" : "年月日" , "實際開工日期" : "年月日" , "竣工日期" : "年月日" , "土地使用分區" : "" , "建築物用途" : "" , "工程造價" : "" , "qtime" : "" , "樓層概要" : [ ] , "地號" : [ ] , "門牌" : [ ] , "縣市別" : "台中市"} , { "_id" : { "$oid" : "60d1cff136f48c39416c860f"} , "執照類別" : "建造執照" , "核發執照字號" : "82府都建建字第06236號" , "原領執照字號" : "" , "變更設計次數" : "00" , "基地面積" : "0㎡" , "建築面積" : "0㎡" , "總樓地板面積" : "0㎡" , "建築物高度" : "0ｍ" , "地下避難面積" : "0㎡" , "法定空地面積" : "0㎡" , "建造類別" : "" , "構造別" : "" , "地上層數" : "0層" , "地下層數" : "0層" , "棟數" : "0棟" , "戶數" : "0戶" , "起造人代表人" : "" , "起造人地址" : "" , "設計人" : "" , "監造人" : "" , "承造人" : "" , "雜項工作物" : "" , "停車空間" : "法定0輛，獎勵0輛，自設0輛" , "發照日期" : "年月日" , "實際開工日期" : "年月日" , "竣工日期" : "年月日" , "土地使用分區" : "" , "建築物用途" : "" , "工程造價" : "" , "qtime" : "" , "樓層概要" : [ ] , "地號" : [ ] , "門牌" : [ ] , "縣市別" : "台中市"} , { "_id" : { "$oid" : "60d1cff136f48c39416c8610"} , "執照類別" : "建造執照" , "核發執照字號" : "82府都建建字第06664號" , "原領執照字號" : "" , "變更設計次數" : "00" , "基地面積" : "0㎡" , "建築面積" : "0㎡" , "總樓地板面積" : "0㎡" , "建築物高度" : "0ｍ" , "地下避難面積" : "0㎡" , "法定空地面積" : "0㎡" , "建造類別" : "" , "構造別" : "" , "地上層數" : "0層" , "地下層數" : "0層" , "棟數" : "0棟" , "戶數" : "0戶" , "起造人代表人" : "" , "起造人地址" : "" , "設計人" : "" , "監造人" : "" , "承造人" : "" , "雜項工作物" : "" , "停車空間" : "法定0輛，獎勵0輛，自設0輛" , "發照日期" : "年月日" , "實際開工日期" : "年月日" , "竣工日期" : "年月日" , "土地使用分區" : "" , "建築物用途" : "" , "工程造價" : "" , "qtime" : "" , "樓層概要" : [ ] , "地號" : [ ] , "門牌" : [ ] , "縣市別" : "台中市"} , { "_id" : { "$oid" : "60d1cff136f48c39416c8611"} , "執照類別" : "建造執照" , "核發執照字號" : "82府都建建字第06665號" , "原領執照字號" : "" , "變更設計次數" : "00" , "基地面積" : "0㎡" , "建築面積" : "0㎡" , "總樓地板面積" : "0㎡" , "建築物高度" : "0ｍ" , "地下避難面積" : "0㎡" , "法定空地面積" : "0㎡" , "建造類別" : "" , "構造別" : "" , "地上層數" : "0層" , "地下層數" : "0層" , "棟數" : "0棟" , "戶數" : "0戶" , "起造人代表人" : "" , "起造人地址" : "" , "設計人" : "" , "監造人" : "" , "承造人" : "" , "雜項工作物" : "" , "停車空間" : "法定0輛，獎勵0輛，自設0輛" , "發照日期" : "年月日" , "實際開工日期" : "年月日" , "竣工日期" : "年月日" , "土地使用分區" : "" , "建築物用途" : "" , "工程造價" : "" , "qtime" : "" , "樓層概要" : [ ] , "地號" : [ ] , "門牌" : [ ] , "縣市別" : "台中市"} , { "_id" : { "$oid" : "60d1cff136f48c39416c8612"} , "執照類別" : "建造執照" , "核發執照字號" : "82府都建建字第06666號" , "原領執照字號" : "" , "變更設計次數" : "00" , "基地面積" : "0㎡" , "建築面積" : "0㎡" , "總樓地板面積" : "0㎡" , "建築物高度" : "0ｍ" , "地下避難面積" : "0㎡" , "法定空地面積" : "0㎡" , "建造類別" : "" , "構造別" : "" , "地上層數" : "0層" , "地下層數" : "0層" , "棟數" : "0棟" , "戶數" : "0戶" , "起造人代表人" : "" , "起造人地址" : "" , "設計人" : "" , "監造人" : "" , "承造人" : "" , "雜項工作物" : "" , "停車空間" : "法定0輛，獎勵0輛，自設0輛" , "發照日期" : "年月日" , "實際開工日期" : "年月日" , "竣工日期" : "年月日" , "土地使用分區" : "" , "建築物用途" : "" , "工程造價" : "" , "qtime" : "" , "樓層概要" : [ ] , "地號" : [ ] , "門牌" : [ ] , "縣市別" : "台中市"} , { "_id" : { "$oid" : "60d1cff136f48c39416c8613"} , "執照類別" : "建造執照" , "核發執照字號" : "82府都建建字第06667號" , "原領執照字號" : "" , "變更設計次數" : "00" , "基地面積" : "0㎡" , "建築面積" : "0㎡" , "總樓地板面積" : "0㎡" , "建築物高度" : "0ｍ" , "地下避難面積" : "0㎡" , "法定空地面積" : "0㎡" , "建造類別" : "" , "構造別" : "" , "地上層數" : "0層" , "地下層數" : "0層" , "棟數" : "0棟" , "戶數" : "0戶" , "起造人代表人" : "" , "起造人地址" : "" , "設計人" : "" , "監造人" : "" , "承造人" : "" , "雜項工作物" : "" , "停車空間" : "法定0輛，獎勵0輛，自設0輛" , "發照日期" : "年月日" , "實際開工日期" : "年月日" , "竣工日期" : "年月日" , "土地使用分區" : "" , "建築物用途" : "" , "工程造價" : "" , "qtime" : "" , "樓層概要" : [ ] , "地號" : [ ] , "門牌" : [ ] , "縣市別" : "台中市"} , { "_id" : { "$oid" : "60d1cff136f48c39416c8614"} , "執照類別" : "建造執照" , "核發執照字號" : "82府都建建字第06668號" , "原領執照字號" : "" , "變更設計次數" : "00" , "基地面積" : "0㎡" , "建築面積" : "0㎡" , "總樓地板面積" : "0㎡" , "建築物高度" : "0ｍ" , "地下避難面積" : "0㎡" , "法定空地面積" : "0㎡" , "建造類別" : "" , "構造別" : "" , "地上層數" : "0層" , "地下層數" : "0層" , "棟數" : "0棟" , "戶數" : "0戶" , "起造人代表人" : "" , "起造人地址" : "" , "設計人" : "" , "監造人" : "" , "承造人" : "" , "雜項工作物" : "" , "停車空間" : "法定0輛，獎勵0輛，自設0輛" , "發照日期" : "年月日" , "實際開工日期" : "年月日" , "竣工日期" : "年月日" , "土地使用分區" : "" , "建築物用途" : "" , "工程造價" : "" , "qtime" : "" , "樓層概要" : [ ] , "地號" : [ ] , "門牌" : [ ] , "縣市別" : "台中市"} , { "_id" : { "$oid" : "60d1cff136f48c39416c8615"} , "執照類別" : "建造執照" , "核發執照字號" : "82府都建建字第06669號" , "原領執照字號" : "" , "變更設計次數" : "00" , "基地面積" : "0㎡" , "建築面積" : "0㎡" , "總樓地板面積" : "0㎡" , "建築物高度" : "0ｍ" , "地下避難面積" : "0㎡" , "法定空地面積" : "0㎡" , "建造類別" : "" , "構造別" : "" , "地上層數" : "0層" , "地下層數" : "0層" , "棟數" : "0棟" , "戶數" : "0戶" , "起造人代表人" : "" , "起造人地址" : "" , "設計人" : "" , "監造人" : "" , "承造人" : "" , "雜項工作物" : "" , "停車空間" : "法定0輛，獎勵0輛，自設0輛" , "發照日期" : "年月日" , "實際開工日期" : "年月日" , "竣工日期" : "年月日" , "土地使用分區" : "" , "建築物用途" : "" , "工程造價" : "" , "qtime" : "" , "樓層概要" : [ ] , "地號" : [ ] , "門牌" : [ ] , "縣市別" : "台中市"} , { "_id" : { "$oid" : "60d1cff136f48c39416c8616"} , "執照類別" : "建造執照" , "核發執照字號" : "82府都建建字第06670號" , "原領執照字號" : "" , "變更設計次數" : "00" , "基地面積" : "0㎡" , "建築面積" : "0㎡" , "總樓地板面積" : "0㎡" , "建築物高度" : "0ｍ" , "地下避難面積" : "0㎡" , "法定空地面積" : "0㎡" , "建造類別" : "" , "構造別" : "" , "地上層數" : "0層" , "地下層數" : "0層" , "棟數" : "0棟" , "戶數" : "0戶" , "起造人代表人" : "" , "起造人地址" : "" , "設計人" : "" , "監造人" : "" , "承造人" : "" , "雜項工作物" : "" , "停車空間" : "法定0輛，獎勵0輛，自設0輛" , "發照日期" : "年月日" , "實際開工日期" : "年月日" , "竣工日期" : "年月日" , "土地使用分區" : "" , "建築物用途" : "" , "工程造價" : "" , "qtime" : "" , "樓層概要" : [ ] , "地號" : [ ] , "門牌" : [ ] , "縣市別" : "台中市"} , { "_id" : { "$oid" : "60d1cff136f48c39416c8617"} , "執照類別" : "建造執照" , "核發執照字號" : "82府都建建字第06672號" , "原領執照字號" : "" , "變更設計次數" : "00" , "基地面積" : "0㎡" , "建築面積" : "0㎡" , "總樓地板面積" : "0㎡" , "建築物高度" : "0ｍ" , "地下避難面積" : "0㎡" , "法定空地面積" : "0㎡" , "建造類別" : "" , "構造別" : "" , "地上層數" : "0層" , "地下層數" : "0層" , "棟數" : "0棟" , "戶數" : "0戶" , "起造人代表人" : "" , "起造人地址" : "" , "設計人" : "" , "監造人" : "" , "承造人" : "" , "雜項工作物" : "" , "停車空間" : "法定0輛，獎勵0輛，自設0輛" , "發照日期" : "年月日" , "實際開工日期" : "年月日" , "竣工日期" : "年月日" , "土地使用分區" : "" , "建築物用途" : "" , "工程造價" : "" , "qtime" : "" , "樓層概要" : [ ] , "地號" : [ ] , "門牌" : [ ] , "縣市別" : "台中市"} , { "_id" : { "$oid" : "60d1cff136f48c39416c8618"} , "執照類別" : "建造執照" , "核發執照字號" : "82府都建建字第06673號" , "原領執照字號" : "" , "變更設計次數" : "00" , "基地面積" : "0㎡" , "建築面積" : "0㎡" , "總樓地板面積" : "0㎡" , "建築物高度" : "0ｍ" , "地下避難面積" : "0㎡" , "法定空地面積" : "0㎡" , "建造類別" : "" , "構造別" : "" , "地上層數" : "0層" , "地下層數" : "0層" , "棟數" : "0棟" , "戶數" : "0戶" , "起造人代表人" : "" , "起造人地址" : "" , "設計人" : "" , "監造人" : "" , "承造人" : "" , "雜項工作物" : "" , "停車空間" : "法定0輛，獎勵0輛，自設0輛" , "發照日期" : "年月日" , "實際開工日期" : "年月日" , "竣工日期" : "年月日" , "土地使用分區" : "" , "建築物用途" : "" , "工程造價" : "" , "qtime" : "" , "樓層概要" : [ ] , "地號" : [ ] , "門牌" : [ ] , "縣市別" : "台中市"} , { "_id" : { "$oid" : "60d1cff136f48c39416c8619"} , "執照類別" : "建造執照" , "核發執照字號" : "82府都建建字第06674號" , "原領執照字號" : "" , "變更設計次數" : "00" , "基地面積" : "0㎡" , "建築面積" : "0㎡" , "總樓地板面積" : "0㎡" , "建築物高度" : "0ｍ" , "地下避難面積" : "0㎡" , "法定空地面積" : "0㎡" , "建造類別" : "" , "構造別" : "" , "地上層數" : "0層" , "地下層數" : "0層" , "棟數" : "0棟" , "戶數" : "0戶" , "起造人代表人" : "" , "起造人地址" : "" , "設計人" : "" , "監造人" : "" , "承造人" : "" , "雜項工作物" : "" , "停車空間" : "法定0輛，獎勵0輛，自設0輛" , "發照日期" : "年月日" , "實際開工日期" : "年月日" , "竣工日期" : "年月日" , "土地使用分區" : "" , "建築物用途" : "" , "工程造價" : "" , "qtime" : "" , "樓層概要" : [ ] , "地號" : [ ] , "門牌" : [ ] , "縣市別" : "台中市"} , { "_id" : { "$oid" : "60d1cff136f48c39416c861a"} , "執照類別" : "建造執照" , "核發執照字號" : "82府都建建字第06677號" , "原領執照字號" : "" , "變更設計次數" : "00" , "基地面積" : "0㎡" , "建築面積" : "0㎡" , "總樓地板面積" : "0㎡" , "建築物高度" : "0ｍ" , "地下避難面積" : "0㎡" , "法定空地面積" : "0㎡" , "建造類別" : "" , "構造別" : "" , "地上層數" : "0層" , "地下層數" : "0層" , "棟數" : "0棟" , "戶數" : "0戶" , "起造人代表人" : "" , "起造人地址" : "" , "設計人" : "" , "監造人" : "" , "承造人" : "" , "雜項工作物" : "" , "停車空間" : "法定0輛，獎勵0輛，自設0輛" , "發照日期" : "年月日" , "實際開工日期" : "年月日" , "竣工日期" : "年月日" , "土地使用分區" : "" , "建築物用途" : "" , "工程造價" : "" , "qtime" : "" , "樓層概要" : [ ] , "地號" : [ ] , "門牌" : [ ] , "縣市別" : "台中市"} , { "_id" : { "$oid" : "60d1cff136f48c39416c861b"} , "執照類別" : "建造執照" , "核發執照字號" : "82府都建建字第06678號" , "原領執照字號" : "" , "變更設計次數" : "00" , "基地面積" : "0㎡" , "建築面積" : "0㎡" , "總樓地板面積" : "0㎡" , "建築物高度" : "0ｍ" , "地下避難面積" : "0㎡" , "法定空地面積" : "0㎡" , "建造類別" : "" , "構造別" : "" , "地上層數" : "0層" , "地下層數" : "0層" , "棟數" : "0棟" , "戶數" : "0戶" , "起造人代表人" : "" , "起造人地址" : "" , "設計人" : "" , "監造人" : "" , "承造人" : "" , "雜項工作物" : "" , "停車空間" : "法定0輛，獎勵0輛，自設0輛" , "發照日期" : "年月日" , "實際開工日期" : "年月日" , "竣工日期" : "年月日" , "土地使用分區" : "" , "建築物用途" : "" , "工程造價" : "" , "qtime" : "" , "樓層概要" : [ ] , "地號" : [ ] , "門牌" : [ ] , "縣市別" : "台中市"} , { "_id" : { "$oid" : "60d1cff136f48c39416c861c"} , "執照類別" : "建造執照" , "核發執照字號" : "82府都建建字第06679號" , "原領執照字號" : "" , "變更設計次數" : "00" , "基地面積" : "0㎡" , "建築面積" : "0㎡" , "總樓地板面積" : "0㎡" , "建築物高度" : "0ｍ" , "地下避難面積" : "0㎡" , "法定空地面積" : "0㎡" , "建造類別" : "" , "構造別" : "" , "地上層數" : "0層" , "地下層數" : "0層" , "棟數" : "0棟" , "戶數" : "0戶" , "起造人代表人" : "" , "起造人地址" : "" , "設計人" : "" , "監造人" : "" , "承造人" : "" , "雜項工作物" : "" , "停車空間" : "法定0輛，獎勵0輛，自設0輛" , "發照日期" : "年月日" , "實際開工日期" : "年月日" , "竣工日期" : "年月日" , "土地使用分區" : "" , "建築物用途" : "" , "工程造價" : "" , "qtime" : "" , "樓層概要" : [ ] , "地號" : [ ] , "門牌" : [ ] , "縣市別" : "台中市"} , { "_id" : { "$oid" : "60d1cff136f48c39416c861d"} , "執照類別" : "建造執照" , "核發執照字號" : "82府都建建字第06680號" , "原領執照字號" : "" , "變更設計次數" : "00" , "基地面積" : "0㎡" , "建築面積" : "0㎡" , "總樓地板面積" : "0㎡" , "建築物高度" : "0ｍ" , "地下避難面積" : "0㎡" , "法定空地面積" : "0㎡" , "建造類別" : "" , "構造別" : "" , "地上層數" : "0層" , "地下層數" : "0層" , "棟數" : "0棟" , "戶數" : "0戶" , "起造人代表人" : "" , "起造人地址" : "" , "設計人" : "" , "監造人" : "" , "承造人" : "" , "雜項工作物" : "" , "停車空間" : "法定0輛，獎勵0輛，自設0輛" , "發照日期" : "年月日" , "實際開工日期" : "年月日" , "竣工日期" : "年月日" , "土地使用分區" : "" , "建築物用途" : "" , "工程造價" : "" , "qtime" : "" , "樓層概要" : [ ] , "地號" : [ ] , "門牌" : [ ] , "縣市別" : "台中市"} , { "_id" : { "$oid" : "60d1cff136f48c39416c861e"} , "執照類別" : "建造執照" , "核發執照字號" : "82府都建建字第06684號" , "原領執照字號" : "" , "變更設計次數" : "00" , "基地面積" : "0㎡" , "建築面積" : "0㎡" , "總樓地板面積" : "0㎡" , "建築物高度" : "0ｍ" , "地下避難面積" : "0㎡" , "法定空地面積" : "0㎡" , "建造類別" : "" , "構造別" : "" , "地上層數" : "0層" , "地下層數" : "0層" , "棟數" : "0棟" , "戶數" : "0戶" , "起造人代表人" : "" , "起造人地址" : "" , "設計人" : "" , "監造人" : "" , "承造人" : "" , "雜項工作物" : "" , "停車空間" : "法定0輛，獎勵0輛，自設0輛" , "發照日期" : "年月日" , "實際開工日期" : "年月日" , "竣工日期" : "年月日" , "土地使用分區" : "" , "建築物用途" : "" , "工程造價" : "" , "qtime" : "" , "樓層概要" : [ ] , "地號" : [ ] , "門牌" : [ ] , "縣市別" : "台中市"} , { "_id" : { "$oid" : "60d1cff136f48c39416c861f"} , "執照類別" : "建造執照" , "核發執照字號" : "82府都建建字第06701號" , "原領執照字號" : "" , "變更設計次數" : "00" , "基地面積" : "0㎡" , "建築面積" : "0㎡" , "總樓地板面積" : "0㎡" , "建築物高度" : "0ｍ" , "地下避難面積" : "0㎡" , "法定空地面積" : "0㎡" , "建造類別" : "" , "構造別" : "" , "地上層數" : "0層" , "地下層數" : "0層" , "棟數" : "0棟" , "戶數" : "0戶" , "起造人代表人" : "" , "起造人地址" : "" , "設計人" : "" , "監造人" : "" , "承造人" : "" , "雜項工作物" : "" , "停車空間" : "法定0輛，獎勵0輛，自設0輛" , "發照日期" : "年月日" , "實際開工日期" : "年月日" , "竣工日期" : "年月日" , "土地使用分區" : "" , "建築物用途" : "" , "工程造價" : "" , "qtime" : "" , "樓層概要" : [ ] , "地號" : [ ] , "門牌" : [ ] , "縣市別" : "台中市"} , { "_id" : { "$oid" : "60d1cff136f48c39416c8620"} , "執照類別" : "建造執照" , "核發執照字號" : "82府都建建字第06702號" , "原領執照字號" : "" , "變更設計次數" : "00" , "基地面積" : "0㎡" , "建築面積" : "0㎡" , "總樓地板面積" : "0㎡" , "建築物高度" : "0ｍ" , "地下避難面積" : "0㎡" , "法定空地面積" : "0㎡" , "建造類別" : "" , "構造別" : "" , "地上層數" : "0層" , "地下層數" : "0層" , "棟數" : "0棟" , "戶數" : "0戶" , "起造人代表人" : "" , "起造人地址" : "" , "設計人" : "" , "監造人" : "" , "承造人" : "" , "雜項工作物" : "" , "停車空間" : "法定0輛，獎勵0輛，自設0輛" , "發照日期" : "年月日" , "實際開工日期" : "年月日" , "竣工日期" : "年月日" , "土地使用分區" : "" , "建築物用途" : "" , "工程造價" : "" , "qtime" : "" , "樓層概要" : [ ] , "地號" : [ ] , "門牌" : [ ] , "縣市別" : "台中市"} , { "_id" : { "$oid" : "60d1cff136f48c39416c8621"} , "執照類別" : "建造執照" , "核發執照字號" : "82府都建建字第06703號" , "原領執照字號" : "" , "變更設計次數" : "00" , "基地面積" : "0㎡" , "建築面積" : "0㎡" , "總樓地板面積" : "0㎡" , "建築物高度" : "0ｍ" , "地下避難面積" : "0㎡" , "法定空地面積" : "0㎡" , "建造類別" : "" , "構造別" : "" , "地上層數" : "0層" , "地下層數" : "0層" , "棟數" : "0棟" , "戶數" : "0戶" , "起造人代表人" : "" , "起造人地址" : "" , "設計人" : "" , "監造人" : "" , "承造人" : "" , "雜項工作物" : "" , "停車空間" : "法定0輛，獎勵0輛，自設0輛" , "發照日期" : "年月日" , "實際開工日期" : "年月日" , "竣工日期" : "年月日" , "土地使用分區" : "" , "建築物用途" : "" , "工程造價" : "" , "qtime" : "" , "樓層概要" : [ ] , "地號" : [ ] , "門牌" : [ ] , "縣市別" : "台中市"} , { "_id" : { "$oid" : "60d1cff136f48c39416c8622"} , "執照類別" : "建造執照" , "核發執照字號" : "82府都建建字第06706號" , "原領執照字號" : "" , "變更設計次數" : "00" , "基地面積" : "0㎡" , "建築面積" : "0㎡" , "總樓地板面積" : "0㎡" , "建築物高度" : "0ｍ" , "地下避難面積" : "0㎡" , "法定空地面積" : "0㎡" , "建造類別" : "" , "構造別" : "" , "地上層數" : "0層" , "地下層數" : "0層" , "棟數" : "0棟" , "戶數" : "0戶" , "起造人代表人" : "" , "起造人地址" : "" , "設計人" : "" , "監造人" : "" , "承造人" : "" , "雜項工作物" : "" , "停車空間" : "法定0輛，獎勵0輛，自設0輛" , "發照日期" : "年月日" , "實際開工日期" : "年月日" , "竣工日期" : "年月日" , "土地使用分區" : "" , "建築物用途" : "" , "工程造價" : "" , "qtime" : "" , "樓層概要" : [ ] , "地號" : [ ] , "門牌" : [ ] , "縣市別" : "台中市"} , { "_id" : { "$oid" : "60d1cff136f48c39416c8623"} , "執照類別" : "建造執照" , "核發執照字號" : "82府都建建字第06707號" , "原領執照字號" : "" , "變更設計次數" : "00" , "基地面積" : "0㎡" , "建築面積" : "0㎡" , "總樓地板面積" : "0㎡" , "建築物高度" : "0ｍ" , "地下避難面積" : "0㎡" , "法定空地面積" : "0㎡" , "建造類別" : "" , "構造別" : "" , "地上層數" : "0層" , "地下層數" : "0層" , "棟數" : "0棟" , "戶數" : "0戶" , "起造人代表人" : "" , "起造人地址" : "" , "設計人" : "" , "監造人" : "" , "承造人" : "" , "雜項工作物" : "" , "停車空間" : "法定0輛，獎勵0輛，自設0輛" , "發照日期" : "年月日" , "實際開工日期" : "年月日" , "竣工日期" : "年月日" , "土地使用分區" : "" , "建築物用途" : "" , "工程造價" : "" , "qtime" : "" , "樓層概要" : [ ] , "地號" : [ ] , "門牌" : [ ] , "縣市別" : "台中市"} , { "_id" : { "$oid" : "60d1cff136f48c39416c8624"} , "執照類別" : "建造執照" , "核發執照字號" : "82府都建建字第06708號" , "原領執照字號" : "" , "變更設計次數" : "00" , "基地面積" : "0㎡" , "建築面積" : "0㎡" , "總樓地板面積" : "0㎡" , "建築物高度" : "0ｍ" , "地下避難面積" : "0㎡" , "法定空地面積" : "0㎡" , "建造類別" : "" , "構造別" : "" , "地上層數" : "0層" , "地下層數" : "0層" , "棟數" : "0棟" , "戶數" : "0戶" , "起造人代表人" : "" , "起造人地址" : "" , "設計人" : "" , "監造人" : "" , "承造人" : "" , "雜項工作物" : "" , "停車空間" : "法定0輛，獎勵0輛，自設0輛" , "發照日期" : "年月日" , "實際開工日期" : "年月日" , "竣工日期" : "年月日" , "土地使用分區" : "" , "建築物用途" : "" , "工程造價" : "" , "qtime" : "" , "樓層概要" : [ ] , "地號" : [ ] , "門牌" : [ ] , "縣市別" : "台中市"} , { "_id" : { "$oid" : "60d1cff136f48c39416c8625"} , "執照類別" : "建造執照" , "核發執照字號" : "82府都建建字第06709號" , "原領執照字號" : "" , "變更設計次數" : "00" , "基地面積" : "0㎡" , "建築面積" : "0㎡" , "總樓地板面積" : "0㎡" , "建築物高度" : "0ｍ" , "地下避難面積" : "0㎡" , "法定空地面積" : "0㎡" , "建造類別" : "" , "構造別" : "" , "地上層數" : "0層" , "地下層數" : "0層" , "棟數" : "0棟" , "戶數" : "0戶" , "起造人代表人" : "" , "起造人地址" : "" , "設計人" : "" , "監造人" : "" , "承造人" : "" , "雜項工作物" : "" , "停車空間" : "法定0輛，獎勵0輛，自設0輛" , "發照日期" : "年月日" , "實際開工日期" : "年月日" , "竣工日期" : "年月日" , "土地使用分區" : "" , "建築物用途" : "" , "工程造價" : "" , "qtime" : "" , "樓層概要" : [ ] , "地號" : [ ] , "門牌" : [ ] , "縣市別" : "台中市"} , { "_id" : { "$oid" : "60d1cff136f48c39416c8626"} , "執照類別" : "建造執照" , "核發執照字號" : "82府都建建字第06710號" , "原領執照字號" : "" , "變更設計次數" : "00" , "基地面積" : "0㎡" , "建築面積" : "0㎡" , "總樓地板面積" : "0㎡" , "建築物高度" : "0ｍ" , "地下避難面積" : "0㎡" , "法定空地面積" : "0㎡" , "建造類別" : "" , "構造別" : "" , "地上層數" : "0層" , "地下層數" : "0層" , "棟數" : "0棟" , "戶數" : "0戶" , "起造人代表人" : "" , "起造人地址" : "" , "設計人" : "" , "監造人" : "" , "承造人" : "" , "雜項工作物" : "" , "停車空間" : "法定0輛，獎勵0輛，自設0輛" , "發照日期" : "年月日" , "實際開工日期" : "年月日" , "竣工日期" : "年月日" , "土地使用分區" : "" , "建築物用途" : "" , "工程造價" : "" , "qtime" : "" , "樓層概要" : [ ] , "地號" : [ ] , "門牌" : [ ] , "縣市別" : "台中市"} , { "_id" : { "$oid" : "60d1cff136f48c39416c8627"} , "執照類別" : "建造執照" , "核發執照字號" : "82府都建建字第06711號" , "原領執照字號" : "" , "變更設計次數" : "00" , "基地面積" : "0㎡" , "建築面積" : "0㎡" , "總樓地板面積" : "0㎡" , "建築物高度" : "0ｍ" , "地下避難面積" : "0㎡" , "法定空地面積" : "0㎡" , "建造類別" : "" , "構造別" : "" , "地上層數" : "0層" , "地下層數" : "0層" , "棟數" : "0棟" , "戶數" : "0戶" , "起造人代表人" : "" , "起造人地址" : "" , "設計人" : "" , "監造人" : "" , "承造人" : "" , "雜項工作物" : "" , "停車空間" : "法定0輛，獎勵0輛，自設0輛" , "發照日期" : "年月日" , "實際開工日期" : "年月日" , "竣工日期" : "年月日" , "土地使用分區" : "" , "建築物用途" : "" , "工程造價" : "" , "qtime" : "" , "樓層概要" : [ ] , "地號" : [ ] , "門牌" : [ ] , "縣市別" : "台中市"} , { "_id" : { "$oid" : "60d1cff136f48c39416c8628"} , "執照類別" : "建造執照" , "核發執照字號" : "82府都建建字第06712號" , "原領執照字號" : "" , "變更設計次數" : "00" , "基地面積" : "0㎡" , "建築面積" : "0㎡" , "總樓地板面積" : "0㎡" , "建築物高度" : "0ｍ" , "地下避難面積" : "0㎡" , "法定空地面積" : "0㎡" , "建造類別" : "" , "構造別" : "" , "地上層數" : "0層" , "地下層數" : "0層" , "棟數" : "0棟" , "戶數" : "0戶" , "起造人代表人" : "" , "起造人地址" : "" , "設計人" : "" , "監造人" : "" , "承造人" : "" , "雜項工作物" : "" , "停車空間" : "法定0輛，獎勵0輛，自設0輛" , "發照日期" : "年月日" , "實際開工日期" : "年月日" , "竣工日期" : "年月日" , "土地使用分區" : "" , "建築物用途" : "" , "工程造價" : "" , "qtime" : "" , "樓層概要" : [ ] , "地號" : [ ] , "門牌" : [ ] , "縣市別" : "台中市"} , { "_id" : { "$oid" : "60d1cff136f48c39416c8629"} , "執照類別" : "建造執照" , "核發執照字號" : "82府都建建字第06713號" , "原領執照字號" : "" , "變更設計次數" : "00" , "基地面積" : "0㎡" , "建築面積" : "0㎡" , "總樓地板面積" : "0㎡" , "建築物高度" : "0ｍ" , "地下避難面積" : "0㎡" , "法定空地面積" : "0㎡" , "建造類別" : "" , "構造別" : "" , "地上層數" : "0層" , "地下層數" : "0層" , "棟數" : "0棟" , "戶數" : "0戶" , "起造人代表人" : "" , "起造人地址" : "" , "設計人" : "" , "監造人" : "" , "承造人" : "" , "雜項工作物" : "" , "停車空間" : "法定0輛，獎勵0輛，自設0輛" , "發照日期" : "年月日" , "實際開工日期" : "年月日" , "竣工日期" : "年月日" , "土地使用分區" : "" , "建築物用途" : "" , "工程造價" : "" , "qtime" : "" , "樓層概要" : [ ] , "地號" : [ ] , "門牌" : [ ] , "縣市別" : "台中市"} , { "_id" : { "$oid" : "60d1cff136f48c39416c862a"} , "執照類別" : "建造執照" , "核發執照字號" : "82府都建建字第06714號" , "原領執照字號" : "" , "變更設計次數" : "00" , "基地面積" : "0㎡" , "建築面積" : "0㎡" , "總樓地板面積" : "0㎡" , "建築物高度" : "0ｍ" , "地下避難面積" : "0㎡" , "法定空地面積" : "0㎡" , "建造類別" : "" , "構造別" : "" , "地上層數" : "0層" , "地下層數" : "0層" , "棟數" : "0棟" , "戶數" : "0戶" , "起造人代表人" : "" , "起造人地址" : "" , "設計人" : "" , "監造人" : "" , "承造人" : "" , "雜項工作物" : "" , "停車空間" : "法定0輛，獎勵0輛，自設0輛" , "發照日期" : "年月日" , "實際開工日期" : "年月日" , "竣工日期" : "年月日" , "土地使用分區" : "" , "建築物用途" : "" , "工程造價" : "" , "qtime" : "" , "樓層概要" : [ ] , "地號" : [ ] , "門牌" : [ ] , "縣市別" : "台中市"} , { "_id" : { "$oid" : "60d1cff136f48c39416c862b"} , "執照類別" : "建造執照" , "核發執照字號" : "82府都建建字第06715號" , "原領執照字號" : "" , "變更設計次數" : "00" , "基地面積" : "0㎡" , "建築面積" : "0㎡" , "總樓地板面積" : "0㎡" , "建築物高度" : "0ｍ" , "地下避難面積" : "0㎡" , "法定空地面積" : "0㎡" , "建造類別" : "" , "構造別" : "" , "地上層數" : "0層" , "地下層數" : "0層" , "棟數" : "0棟" , "戶數" : "0戶" , "起造人代表人" : "" , "起造人地址" : "" , "設計人" : "" , "監造人" : "" , "承造人" : "" , "雜項工作物" : "" , "停車空間" : "法定0輛，獎勵0輛，自設0輛" , "發照日期" : "年月日" , "實際開工日期" : "年月日" , "竣工日期" : "年月日" , "土地使用分區" : "" , "建築物用途" : "" , "工程造價" : "" , "qtime" : "" , "樓層概要" : [ ] , "地號" : [ ] , "門牌" : [ ] , "縣市別" : "台中市"} , { "_id" : { "$oid" : "60d1cff136f48c39416c862c"} , "執照類別" : "建造執照" , "核發執照字號" : "82府都建建字第06730號" , "原領執照字號" : "" , "變更設計次數" : "00" , "基地面積" : "0㎡" , "建築面積" : "0㎡" , "總樓地板面積" : "0㎡" , "建築物高度" : "0ｍ" , "地下避難面積" : "0㎡" , "法定空地面積" : "0㎡" , "建造類別" : "" , "構造別" : "" , "地上層數" : "0層" , "地下層數" : "0層" , "棟數" : "0棟" , "戶數" : "0戶" , "起造人代表人" : "" , "起造人地址" : "" , "設計人" : "" , "監造人" : "" , "承造人" : "" , "雜項工作物" : "" , "停車空間" : "法定0輛，獎勵0輛，自設0輛" , "發照日期" : "年月日" , "實際開工日期" : "年月日" , "竣工日期" : "年月日" , "土地使用分區" : "" , "建築物用途" : "" , "工程造價" : "" , "qtime" : "" , "樓層概要" : [ ] , "地號" : [ ] , "門牌" : [ ] , "縣市別" : "台中市"} , { "_id" : { "$oid" : "60d1cff136f48c39416c862d"} , "執照類別" : "建造執照" , "核發執照字號" : "82府都建建字第06731號" , "原領執照字號" : "" , "變更設計次數" : "00" , "基地面積" : "0㎡" , "建築面積" : "0㎡" , "總樓地板面積" : "0㎡" , "建築物高度" : "0ｍ" , "地下避難面積" : "0㎡" , "法定空地面積" : "0㎡" , "建造類別" : "" , "構造別" : "" , "地上層數" : "0層" , "地下層數" : "0層" , "棟數" : "0棟" , "戶數" : "0戶" , "起造人代表人" : "" , "起造人地址" : "" , "設計人" : "" , "監造人" : "" , "承造人" : "" , "雜項工作物" : "" , "停車空間" : "法定0輛，獎勵0輛，自設0輛" , "發照日期" : "年月日" , "實際開工日期" : "年月日" , "竣工日期" : "年月日" , "土地使用分區" : "" , "建築物用途" : "" , "工程造價" : "" , "qtime" : "" , "樓層概要" : [ ] , "地號" : [ ] , "門牌" : [ ] , "縣市別" : "台中市"} , { "_id" : { "$oid" : "60d1cff136f48c39416c862e"} , "執照類別" : "建造執照" , "核發執照字號" : "104中都建字第00793號" , "原領執照字號" : "104中都建字第00793號" , "變更設計次數" : "01" , "基地面積" : "273.85㎡" , "建築面積" : "125.52㎡" , "總樓地板面積" : "522.02㎡" , "建築物高度" : "14.3ｍ" , "地下避難面積" : "0㎡" , "法定空地面積" : "136.93㎡" , "建造類別" : "新建" , "構造別" : "鋼筋混凝土造" , "地上層數" : "4層" , "地下層數" : "0層" , "棟數" : "2棟" , "戶數" : "2戶" , "起造人代表人" : "高照建設有限公司負責人:江靜祥" , "起造人地址" : "臺中ＯＯＯＯＯＯＯＯＯＯＯＯＯＯＯ" , "設計人" : "蕭添發" , "監造人" : "蕭添發" , "承造人" : "名家營造有限公司" , "雜項工作物" : "" , "停車空間" : "法定3輛，獎勵0輛，自設1輛" , "發照日期" : "105年01月19日" , "實際開工日期" : "年月日" , "竣工日期" : "年月日" , "土地使用分區" : "第一種住宅區" , "建築物用途" : "住宅" , "工程造價" : "3529000" , "qtime" : "10501" , "樓層概要" : [ { "樓層別" : "地上001層" , "樓層高度" : "3.95ｍ" , "樓層面積" : "125.52㎡" , "樓層用途" : "停車空間、管道間、樓梯間、儲藏室"} , { "樓層別" : "地上002層" , "樓層高度" : "3.3ｍ" , "樓層面積" : "125.52㎡" , "樓層用途" : "H2住宅"} , { "樓層別" : "地上003層" , "樓層高度" : "3.3ｍ" , "樓層面積" : "125.52㎡" , "樓層用途" : "H2住宅"} , { "樓層別" : "地上004層" , "樓層高度" : "3.3ｍ" , "樓層面積" : "95.58㎡" , "樓層用途" : "H2住宅"} , { "樓層別" : "突出物001層" , "樓層高度" : "3.3ｍ" , "樓層面積" : "49.88㎡" , "樓層用途" : "樓梯間"}] , "地號" : [ { "行政區" : "臺中市東區" , "地段" : "旱清段" , "地號母號" : "0076" , "地號子號" : "0000"} , { "行政區" : "臺中市東區" , "地段" : "旱清段" , "地號母號" : "0076" , "地號子號" : "0001"}] , "門牌" : [ { "戶號" : "A1" , "行政區" : "" , "村里鄰" : "" , "路街段巷弄" : "" , "號" : "" , "樓" : ""} , { "戶號" : "A2" , "行政區" : "" , "村里鄰" : "" , "路街段巷弄" : "" , "號" : "" , "樓" : ""}] , "縣市別" : "台中市"} , { "_id" : { "$oid" : "60d1cff136f48c39416c862f"} , "執照類別" : "建造執照" , "核發執照字號" : "104中都建字第00794號" , "原領執照字號" : "104中都建字第00794號" , "變更設計次數" : "01" , "基地面積" : "303.18㎡" , "建築面積" : "139.68㎡" , "總樓地板面積" : "552.2㎡" , "建築物高度" : "14.55ｍ" , "地下避難面積" : "0㎡" , "法定空地面積" : "151.59㎡" , "建造類別" : "新建" , "構造別" : "鋼筋混凝土造" , "地上層數" : "4層" , "地下層數" : "0層" , "棟數" : "2棟" , "戶數" : "2戶" , "起造人代表人" : "高照建設有限公司負責人:江靜祥" , "起造人地址" : "臺中ＯＯＯＯＯＯＯＯＯＯＯＯＯＯＯ" , "設計人" : "蕭添發" , "監造人" : "蕭添發" , "承造人" : "名家營造有限公司" , "雜項工作物" : "" , "停車空間" : "法定3輛，獎勵0輛，自設0輛" , "發照日期" : "105年01月19日" , "實際開工日期" : "年月日" , "竣工日期" : "年月日" , "土地使用分區" : "第一種住宅區" , "建築物用途" : "住宅" , "工程造價" : "3714000" , "qtime" : "10501" , "樓層概要" : [ { "樓層別" : "地上001層" , "樓層高度" : "4.2ｍ" , "樓層面積" : "137.5㎡" , "樓層用途" : "停車空間、管道間、樓梯間、儲藏室"} , { "樓層別" : "地上002層" , "樓層高度" : "3.3ｍ" , "樓層面積" : "135.86㎡" , "樓層用途" : "H2住宅"} , { "樓層別" : "地上003層" , "樓層高度" : "3.3ｍ" , "樓層面積" : "136㎡" , "樓層用途" : "H2住宅"} , { "樓層別" : "地上004層" , "樓層高度" : "3.3ｍ" , "樓層面積" : "92.98㎡" , "樓層用途" : "H2住宅"} , { "樓層別" : "突出物001層" , "樓層高度" : "3.3ｍ" , "樓層面積" : "49.86㎡" , "樓層用途" : "樓梯間"}] , "地號" : [ { "行政區" : "臺中市東區" , "地段" : "旱清段" , "地號母號" : "0076" , "地號子號" : "0002"} , { "行政區" : "臺中市東區" , "地段" : "旱清段" , "地號母號" : "0076" , "地號子號" : "0003"}] , "門牌" : [ { "戶號" : "B1" , "行政區" : "" , "村里鄰" : "" , "路街段巷弄" : "" , "號" : "" , "樓" : ""} , { "戶號" : "B2" , "行政區" : "" , "村里鄰" : "" , "路街段巷弄" : "" , "號" : "" , "樓" : ""}] , "縣市別" : "台中市"} , { "_id" : { "$oid" : "60d1cff136f48c39416c8630"} , "執照類別" : "建造執照" , "核發執照字號" : "105中都建字第00083號" , "原領執照字號" : "" , "變更設計次數" : "00" , "基地面積" : "462㎡" , "建築面積" : "204.88㎡" , "總樓地板面積" : "844.33㎡" , "建築物高度" : "13.95ｍ" , "地下避難面積" : "0㎡" , "法定空地面積" : "182.5㎡" , "建造類別" : "新建" , "構造別" : "鋼筋混凝土造" , "地上層數" : "4層" , "地下層數" : "0層" , "棟數" : "1棟" , "戶數" : "1戶" , "起造人代表人" : "陳霖Ｏ" , "起造人地址" : "臺中ＯＯＯＯＯＯＯＯＯＯＯＯＯＯＯ" , "設計人" : "葉水龍" , "監造人" : "葉水龍" , "承造人" : "仰哲營造有限公司" , "雜項工作物" : "" , "停車空間" : "法定3輛，獎勵0輛，自設0輛" , "發照日期" : "105年01月13日" , "實際開工日期" : "105年03月16日" , "竣工日期" : "年月日" , "土地使用分區" : "農業區建地目" , "建築物用途" : "住宅" , "工程造價" : "5421000" , "qtime" : "10501" , "樓層概要" : [ { "樓層別" : "地上001層" , "樓層高度" : "4.2ｍ" , "樓層面積" : "204.88㎡" , "樓層用途" : "H2住房"} , { "樓層別" : "地上002層" , "樓層高度" : "3.2ｍ" , "樓層面積" : "204.88㎡" , "樓層用途" : "H2住房"} , { "樓層別" : "地上003層" , "樓層高度" : "3.2ｍ" , "樓層面積" : "204.88㎡" , "樓層用途" : "H2住房"} , { "樓層別" : "地上004層" , "樓層高度" : "3.2ｍ" , "樓層面積" : "204.88㎡" , "樓層用途" : "H2住房"} , { "樓層別" : "突出物001層" , "樓層高度" : "3.2ｍ" , "樓層面積" : "24.81㎡" , "樓層用途" : "樓梯間"}] , "地號" : [ { "行政區" : "臺中市神岡區" , "地段" : "社口段" , "地號母號" : "0039" , "地號子號" : "0006"}] , "門牌" : [ { "戶號" : "" , "行政區" : "臺中市神岡區" , "村里鄰" : "" , "路街段巷弄" : "" , "號" : "" , "樓" : ""}] , "縣市別" : "台中市"} , { "_id" : { "$oid" : "60d1cff136f48c39416c8631"} , "執照類別" : "建造執照" , "核發執照字號" : "105中都建字第00008號" , "原領執照字號" : "" , "變更設計次數" : "00" , "基地面積" : "160.65㎡" , "建築面積" : "61.36㎡" , "總樓地板面積" : "223.65㎡" , "建築物高度" : "10.8ｍ" , "地下避難面積" : "0㎡" , "法定空地面積" : "94.16㎡" , "建造類別" : "新建" , "構造別" : "鋼筋混凝土造" , "地上層數" : "3層" , "地下層數" : "0層" , "棟數" : "2棟" , "戶數" : "2戶" , "起造人代表人" : "黃碧Ｏ" , "起造人地址" : "臺中ＯＯＯＯＯＯＯＯＯＯＯＯＯＯＯ" , "設計人" : "王毓翔" , "監造人" : "王毓翔" , "承造人" : "昕懋營造有限公司" , "雜項工作物" : "" , "停車空間" : "法定0輛，獎勵0輛，自設0輛" , "發照日期" : "105年01月04日" , "實際開工日期" : "105年08月19日" , "竣工日期" : "年月日" , "土地使用分區" : "一般農業區丙種建築用地" , "建築物用途" : "住宅" , "工程造價" : "1386000" , "qtime" : "10501" , "樓層概要" : [ { "樓層別" : "A1,2棟地上001層" , "樓層高度" : "3.6ｍ" , "樓層面積" : "61.36㎡" , "樓層用途" : "H2住宅"} , { "樓層別" : "A1,2棟地上002層" , "樓層高度" : "3.4ｍ" , "樓層面積" : "61.36㎡" , "樓層用途" : "H2住宅"} , { "樓層別" : "A1,2棟地上003層" , "樓層高度" : "3.2ｍ" , "樓層面積" : "61.36㎡" , "樓層用途" : "H2住宅"} , { "樓層別" : "A1,2棟突出物001層" , "樓層高度" : "3ｍ" , "樓層面積" : "39.57㎡" , "樓層用途" : "樓梯間"}] , "地號" : [ { "行政區" : "臺中市大肚區" , "地段" : "瑞井段" , "地號母號" : "1378" , "地號子號" : "0000"} , { "行政區" : "臺中市大肚區" , "地段" : "瑞井段" , "地號母號" : "1379" , "地號子號" : "0000"}] , "門牌" : [ { "戶號" : "A1" , "行政區" : "" , "村里鄰" : "" , "路街段巷弄" : "" , "號" : "" , "樓" : ""} , { "戶號" : "A2" , "行政區" : "" , "村里鄰" : "" , "路街段巷弄" : "" , "號" : "" , "樓" : ""}] , "縣市別" : "台中市"} , { "_id" : { "$oid" : "60d1cff136f48c39416c8632"} , "執照類別" : "建造執照" , "核發執照字號" : "(79)工建建字第02552號" , "原領執照字號" : "" , "變更設計次數" : "00" , "基地面積" : "0㎡" , "建築面積" : "0㎡" , "總樓地板面積" : "0㎡" , "建築物高度" : "0ｍ" , "地下避難面積" : "0㎡" , "法定空地面積" : "0㎡" , "建造類別" : "" , "構造別" : "" , "地上層數" : "0層" , "地下層數" : "0層" , "棟數" : "0棟" , "戶數" : "0戶" , "起造人代表人" : "" , "起造人地址" : "" , "設計人" : "" , "監造人" : "" , "承造人" : "" , "雜項工作物" : "" , "停車空間" : "法定0輛，獎勵0輛，自設0輛" , "發照日期" : "年月日" , "實際開工日期" : "年月日" , "竣工日期" : "年月日" , "土地使用分區" : "" , "建築物用途" : "" , "工程造價" : "" , "qtime" : "" , "樓層概要" : [ ] , "地號" : [ ] , "門牌" : [ ] , "縣市別" : "台中市"} , { "_id" : { "$oid" : "60d1cff136f48c39416c8633"} , "執照類別" : "建造執照" , "核發執照字號" : "(79)工建建字第02554號" , "原領執照字號" : "" , "變更設計次數" : "00" , "基地面積" : "0㎡" , "建築面積" : "0㎡" , "總樓地板面積" : "0㎡" , "建築物高度" : "0ｍ" , "地下避難面積" : "0㎡" , "法定空地面積" : "0㎡" , "建造類別" : "" , "構造別" : "" , "地上層數" : "0層" , "地下層數" : "0層" , "棟數" : "0棟" , "戶數" : "0戶" , "起造人代表人" : "" , "起造人地址" : "" , "設計人" : "" , "監造人" : "" , "承造人" : "" , "雜項工作物" : "" , "停車空間" : "法定0輛，獎勵0輛，自設0輛" , "發照日期" : "年月日" , "實際開工日期" : "年月日" , "竣工日期" : "年月日" , "土地使用分區" : "" , "建築物用途" : "" , "工程造價" : "" , "qtime" : "" , "樓層概要" : [ ] , "地號" : [ ] , "門牌" : [ ] , "縣市別" : "台中市"} , { "_id" : { "$oid" : "60d1cff136f48c39416c8634"} , "執照類別" : "建造執照" , "核發執照字號" : "(79)工建建字第02555號" , "原領執照字號" : "" , "變更設計次數" : "00" , "基地面積" : "0㎡" , "建築面積" : "0㎡" , "總樓地板面積" : "0㎡" , "建築物高度" : "0ｍ" , "地下避難面積" : "0㎡" , "法定空地面積" : "0㎡" , "建造類別" : "" , "構造別" : "" , "地上層數" : "0層" , "地下層數" : "0層" , "棟數" : "0棟" , "戶數" : "0戶" , "起造人代表人" : "" , "起造人地址" : "" , "設計人" : "" , "監造人" : "" , "承造人" : "" , "雜項工作物" : "" , "停車空間" : "法定0輛，獎勵0輛，自設0輛" , "發照日期" : "年月日" , "實際開工日期" : "年月日" , "竣工日期" : "年月日" , "土地使用分區" : "" , "建築物用途" : "" , "工程造價" : "" , "qtime" : "" , "樓層概要" : [ ] , "地號" : [ ] , "門牌" : [ ] , "縣市別" : "台中市"} , { "_id" : { "$oid" : "60d1cff136f48c39416c8635"} , "執照類別" : "建造執照" , "核發執照字號" : "(79)工建建字第02556號" , "原領執照字號" : "" , "變更設計次數" : "00" , "基地面積" : "0㎡" , "建築面積" : "0㎡" , "總樓地板面積" : "0㎡" , "建築物高度" : "0ｍ" , "地下避難面積" : "0㎡" , "法定空地面積" : "0㎡" , "建造類別" : "" , "構造別" : "" , "地上層數" : "0層" , "地下層數" : "0層" , "棟數" : "0棟" , "戶數" : "0戶" , "起造人代表人" : "" , "起造人地址" : "" , "設計人" : "" , "監造人" : "" , "承造人" : "" , "雜項工作物" : "" , "停車空間" : "法定0輛，獎勵0輛，自設0輛" , "發照日期" : "年月日" , "實際開工日期" : "年月日" , "竣工日期" : "年月日" , "土地使用分區" : "" , "建築物用途" : "" , "工程造價" : "" , "qtime" : "" , "樓層概要" : [ ] , "地號" : [ ] , "門牌" : [ ] , "縣市別" : "台中市"} , { "_id" : { "$oid" : "60d1cff136f48c39416c8636"} , "執照類別" : "建造執照" , "核發執照字號" : "(79)工建建字第02557號" , "原領執照字號" : "" , "變更設計次數" : "00" , "基地面積" : "0㎡" , "建築面積" : "0㎡" , "總樓地板面積" : "0㎡" , "建築物高度" : "0ｍ" , "地下避難面積" : "0㎡" , "法定空地面積" : "0㎡" , "建造類別" : "" , "構造別" : "" , "地上層數" : "0層" , "地下層數" : "0層" , "棟數" : "0棟" , "戶數" : "0戶" , "起造人代表人" : "" , "起造人地址" : "" , "設計人" : "" , "監造人" : "" , "承造人" : "" , "雜項工作物" : "" , "停車空間" : "法定0輛，獎勵0輛，自設0輛" , "發照日期" : "年月日" , "實際開工日期" : "年月日" , "竣工日期" : "年月日" , "土地使用分區" : "" , "建築物用途" : "" , "工程造價" : "" , "qtime" : "" , "樓層概要" : [ ] , "地號" : [ ] , "門牌" : [ ] , "縣市別" : "台中市"}]} 